{"id":"5/13/1979","name":"1979-05-13","date":"0001-01-01T00:00:00","entries":[{"id":"1-across","group":["1-across"],"separatorLocations":{},"number":1,"humanNumber":"1","clue":" Fast-food shop","direction":"across","length":4,"position":{"x":0,"y":0},"solution":"DELI"},{"id":"5-across","group":["5-across"],"separatorLocations":{},"number":5,"humanNumber":"5","clue":" Ballerina's knee bend","direction":"across","length":4,"position":{"x":5,"y":0},"solution":"PLIE"},{"id":"9-across","group":["9-across"],"separatorLocations":{},"number":9,"humanNumber":"9","clue":" Towel fabric","direction":"across","length":5,"position":{"x":10,"y":0},"solution":"CRASH"},{"id":"14-across","group":["14-across"],"separatorLocations":{},"number":14,"humanNumber":"14","clue":" Scenic view","direction":"across","length":5,"position":{"x":1,"y":1},"solution":"SCAPE"},{"id":"19-across","group":["19-across"],"separatorLocations":{},"number":19,"humanNumber":"19","clue":" Buck heroine","direction":"across","length":4,"position":{"x":6,"y":1},"solution":"OLAN"},{"id":"20-across","group":["20-across"],"separatorLocations":{},"number":20,"humanNumber":"20","clue":" Norman or Edward","direction":"across","length":4,"position":{"x":11,"y":1},"solution":"LEAR"},{"id":"21-across","group":["21-across"],"separatorLocations":{},"number":21,"humanNumber":"21","clue":" Word of surprise","direction":"across","length":5,"position":{"x":1,"y":2},"solution":"HELLO"},{"id":"22-across","group":["22-across"],"separatorLocations":{},"number":22,"humanNumber":"22","clue":" Lucubrated","direction":"across","length":5,"position":{"x":7,"y":2},"solution":"PORED"},{"id":"23-across","group":["23-across"],"separatorLocations":{},"number":23,"humanNumber":"23","clue":" Start of a verse","direction":"across","length":21,"position":{"x":12,"y":2},"solution":"NOWTHATMAMASLIBERATED"},{"id":"27-across","group":["27-across"],"separatorLocations":{},"number":27,"humanNumber":"27","clue":" Romberg's forte","direction":"across","length":8,"position":{"x":3,"y":4},"solution":"OPERETTA"},{"id":"28-across","group":["28-across"],"separatorLocations":{},"number":28,"humanNumber":"28","clue":" Insect: Comb. form","direction":"across","length":5,"position":{"x":12,"y":4},"solution":"ENTOM"},{"id":"29-across","group":["29-across"],"separatorLocations":{},"number":29,"humanNumber":"29","clue":" Repetitive recital","direction":"across","length":6,"position":{"x":3,"y":5},"solution":"LITANY"},{"id":"30-across","group":["30-across"],"separatorLocations":{},"number":30,"humanNumber":"30","clue":" R &amp; R spots","direction":"across","length":7,"position":{"x":9,"y":5},"solution":"RESORTS"},{"id":"31-across","group":["31-across"],"separatorLocations":{},"number":31,"humanNumber":"31","clue":" Aspect","direction":"across","length":5,"position":{"x":2,"y":6},"solution":"FACET"},{"id":"32-across","group":["32-across"],"separatorLocations":{},"number":32,"humanNumber":"32","clue":" Schnapps","direction":"across","length":3,"position":{"x":8,"y":6},"solution":"GIN"},{"id":"33-across","group":["33-across"],"separatorLocations":{},"number":33,"humanNumber":"33","clue":" Finger sign","direction":"across","length":3,"position":{"x":3,"y":7},"solution":"VEE"},{"id":"34-across","group":["34-across"],"separatorLocations":{},"number":34,"humanNumber":"34","clue":" Was homesick","direction":"across","length":5,"position":{"x":7,"y":7},"solution":"PINED"},{"id":"35-across","group":["35-across"],"separatorLocations":{},"number":35,"humanNumber":"35","clue":" Cellaret","direction":"across","length":8,"position":{"x":13,"y":7},"solution":"TANTALUS"},{"id":"40-across","group":["40-across"],"separatorLocations":{},"number":40,"humanNumber":"40","clue":" Like an impala","direction":"across","length":5,"position":{"x":6,"y":8},"solution":"FLEET"},{"id":"43-across","group":["43-across"],"separatorLocations":{},"number":43,"humanNumber":"43","clue":" Yarborough, e.g.","direction":"across","length":4,"position":{"x":12,"y":8},"solution":"BUST"},{"id":"44-across","group":["44-across"],"separatorLocations":{},"number":44,"humanNumber":"44","clue":" Chan's expression","direction":"across","length":4,"position":{"x":3,"y":9},"solution":"AHSO"},{"id":"45-across","group":["45-across"],"separatorLocations":{},"number":45,"humanNumber":"45","clue":" Knucklehead","direction":"across","length":4,"position":{"x":8,"y":9},"solution":"DOPE"},{"id":"46-across","group":["46-across"],"separatorLocations":{},"number":46,"humanNumber":"46","clue":" Second line of verse","direction":"across","length":21,"position":{"x":12,"y":9},"solution":"REDROSESHOLDNOPROMISE"},{"id":"51-across","group":["51-across"],"separatorLocations":{},"number":51,"humanNumber":"51","clue":" Overlook","direction":"across","length":4,"position":{"x":3,"y":11},"solution":"OMIT"},{"id":"52-across","group":["52-across"],"separatorLocations":{},"number":52,"humanNumber":"52","clue":" Say grace","direction":"across","length":4,"position":{"x":8,"y":11},"solution":"PRAY"},{"id":"53-across","group":["53-across"],"separatorLocations":{},"number":53,"humanNumber":"53","clue":" Avant-garde","direction":"across","length":5,"position":{"x":13,"y":11},"solution":"OUTRE"},{"id":"54-across","group":["54-across"],"separatorLocations":{},"number":54,"humanNumber":"54","clue":" Stuck","direction":"across","length":5,"position":{"x":4,"y":12},"solution":"MIRED"},{"id":"55-across","group":["55-across"],"separatorLocations":{},"number":55,"humanNumber":"55","clue":" Hood's weapon","direction":"across","length":3,"position":{"x":9,"y":12},"solution":"GAT"},{"id":"56-across","group":["56-across"],"separatorLocations":{},"number":56,"humanNumber":"56","clue":" Tall story","direction":"across","length":4,"position":{"x":13,"y":12},"solution":"YARN"},{"id":"57-across","group":["57-across"],"separatorLocations":{},"number":57,"humanNumber":"57","clue":" Actress Jeanne","direction":"across","length":5,"position":{"x":3,"y":13},"solution":"CRAIN"},{"id":"58-across","group":["58-across"],"separatorLocations":{},"number":58,"humanNumber":"58","clue":" Guarantee","direction":"across","length":6,"position":{"x":9,"y":13},"solution":"SURETY"},{"id":"59-across","group":["59-across"],"separatorLocations":{},"number":59,"humanNumber":"59","clue":" Impugn","direction":"across","length":4,"position":{"x":3,"y":14},"solution":"DENY"},{"id":"60-across","group":["60-across"],"separatorLocations":{},"number":60,"humanNumber":"60","clue":" Space pioneer","direction":"across","length":5,"position":{"x":8,"y":14},"solution":"GLENN"},{"id":"61-across","group":["61-across"],"separatorLocations":{},"number":61,"humanNumber":"61","clue":" Chigger","direction":"across","length":4,"position":{"x":14,"y":14},"solution":"MITE"},{"id":"62-across","group":["62-across"],"separatorLocations":{},"number":62,"humanNumber":"62","clue":" Construction workers","direction":"across","length":6,"position":{"x":6,"y":15},"solution":"MASONS"},{"id":"65-across","group":["65-across"],"separatorLocations":{},"number":65,"humanNumber":"65","clue":" Winged","direction":"across","length":5,"position":{"x":13,"y":15},"solution":"ALATE"},{"id":"66-across","group":["66-across"],"separatorLocations":{},"number":66,"humanNumber":"66","clue":" Cold wind in Peru","direction":"across","length":4,"position":{"x":4,"y":16},"solution":"PUNA"},{"id":"67-across","group":["67-across"],"separatorLocations":{},"number":67,"humanNumber":"67","clue":" Intelligence","direction":"across","length":3,"position":{"x":9,"y":16},"solution":"WIT"},{"id":"70-across","group":["70-across"],"separatorLocations":{},"number":70,"humanNumber":"70","clue":" Bright-eyed","direction":"across","length":5,"position":{"x":12,"y":16},"solution":"ALERT"},{"id":"71-across","group":["71-across"],"separatorLocations":{},"number":71,"humanNumber":"71","clue":" Kit Carson was one","direction":"across","length":5,"position":{"x":3,"y":17},"solution":"SCOUT"},{"id":"72-across","group":["72-across"],"separatorLocations":{},"number":72,"humanNumber":"72","clue":" Soil layers","direction":"across","length":4,"position":{"x":9,"y":17},"solution":"SOLA"},{"id":"73-across","group":["73-across"],"separatorLocations":{},"number":73,"humanNumber":"73","clue":" Princess, in Punjab","direction":"across","length":4,"position":{"x":14,"y":17},"solution":"RANI"},{"id":"74-across","group":["74-across"],"separatorLocations":{},"number":74,"humanNumber":"74","clue":" Third line of verse","direction":"across","length":21,"position":{"x":3,"y":18},"solution":"FORMAMAHASANTICIPATED"},{"id":"78-across","group":["78-across"],"separatorLocations":{},"number":78,"humanNumber":"78","clue":" Year in the reign of Sweyn I","direction":"across","length":4,"position":{"x":9,"y":19},"solution":"IOII"},{"id":"79-across","group":["79-across"],"separatorLocations":{},"number":79,"humanNumber":"79","clue":" Encourage","direction":"across","length":4,"position":{"x":14,"y":19},"solution":"ABET"},{"id":"80-across","group":["80-across"],"separatorLocations":{},"number":80,"humanNumber":"80","clue":" Pittypat in \"G.W.T.W.\"","direction":"across","length":4,"position":{"x":5,"y":20},"solution":"AUNT"},{"id":"81-across","group":["81-across"],"separatorLocations":{},"number":81,"humanNumber":"81","clue":" Posh","direction":"across","length":5,"position":{"x":10,"y":20},"solution":"RITZY"},{"id":"82-across","group":["82-across"],"separatorLocations":{},"number":82,"humanNumber":"82","clue":" Given to a false show","direction":"across","length":8,"position":{"x":0,"y":21},"solution":"AFFECTED"},{"id":"84-across","group":["84-across"],"separatorLocations":{},"number":84,"humanNumber":"84","clue":" Needle","direction":"across","length":5,"position":{"x":9,"y":21},"solution":"TAUNT"},{"id":"86-across","group":["86-across"],"separatorLocations":{},"number":86,"humanNumber":"86","clue":" Marsh","direction":"across","length":3,"position":{"x":0,"y":22},"solution":"FEN"},{"id":"87-across","group":["87-across"],"separatorLocations":{},"number":87,"humanNumber":"87","clue":" \"Ben ___\"","direction":"across","length":3,"position":{"x":10,"y":22},"solution":"HUR"},{"id":"88-across","group":["88-across"],"separatorLocations":{},"number":88,"humanNumber":"88","clue":" Eruption","direction":"across","length":5,"position":{"x":14,"y":22},"solution":"BURST"},{"id":"89-across","group":["89-across"],"separatorLocations":{},"number":89,"humanNumber":"89","clue":" Poem by Shelley: 1816","direction":"across","length":7,"position":{"x":5,"y":23},"solution":"ALASTOR"},{"id":"93-across","group":["93-across"],"separatorLocations":{},"number":93,"humanNumber":"93","clue":" Openness","direction":"across","length":6,"position":{"x":12,"y":23},"solution":"CANDOR"},{"id":"97-across","group":["97-across"],"separatorLocations":{},"number":97,"humanNumber":"97","clue":" Banks of baseball","direction":"across","length":5,"position":{"x":4,"y":24},"solution":"ERNIE"},{"id":"98-across","group":["98-across"],"separatorLocations":{},"number":98,"humanNumber":"98","clue":" Sedentary","direction":"across","length":8,"position":{"x":10,"y":24},"solution":"INACTIVE"},{"id":"99-across","group":["99-across"],"separatorLocations":{},"number":99,"humanNumber":"99","clue":" Last line of verse","direction":"across","length":21,"position":{"x":3,"y":25},"solution":"AWEEKENDINSAINTTHOMAS"},{"id":"102-across","group":["102-across"],"separatorLocations":{},"number":102,"humanNumber":"102","clue":" Elbe tributary","direction":"across","length":5,"position":{"x":9,"y":26},"solution":"SAALE"},{"id":"103-across","group":["103-across"],"separatorLocations":{},"number":103,"humanNumber":"103","clue":" Shoelace tip","direction":"across","length":5,"position":{"x":0,"y":27},"solution":"AGLET"},{"id":"104-across","group":["104-across"],"separatorLocations":{},"number":104,"humanNumber":"104","clue":" Hammett heroine","direction":"across","length":4,"position":{"x":6,"y":27},"solution":"NORA"},{"id":"105-across","group":["105-across"],"separatorLocations":{},"number":105,"humanNumber":"105","clue":" Pictorial presswork","direction":"across","length":4,"position":{"x":11,"y":27},"solution":"ROTO"},{"id":"106-across","group":["106-across"],"separatorLocations":{},"number":106,"humanNumber":"106","clue":" Tippecanoe's running mate","direction":"across","length":5,"position":{"x":0,"y":28},"solution":"TYLER"},{"id":"107-across","group":["107-across"],"separatorLocations":{},"number":107,"humanNumber":"107","clue":" Abzug","direction":"across","length":5,"position":{"x":6,"y":28},"solution":"BELLA"},{"id":"108-across","group":["108-across"],"separatorLocations":{},"number":108,"humanNumber":"108","clue":" \"Too bad!\"","direction":"across","length":4,"position":{"x":12,"y":28},"solution":"ALAS"},{"id":"109-across","group":["109-across"],"separatorLocations":{},"number":109,"humanNumber":"109","clue":" TV talking horse","direction":"across","length":4,"position":{"x":2,"y":29},"solution":"MRED"},{"id":"1-down","group":["1-down"],"separatorLocations":{},"number":1,"humanNumber":"1","clue":" Carnegie was one","direction":"down","length":5,"position":{"x":0,"y":0},"solution":"DONOR"},{"id":"2-down","group":["2-down"],"separatorLocations":{},"number":2,"humanNumber":"2","clue":" Marry on the run","direction":"down","length":5,"position":{"x":1,"y":0},"solution":"ELOPE"},{"id":"3-down","group":["3-down"],"separatorLocations":{},"number":3,"humanNumber":"3","clue":" Sing Sing's famed warden","direction":"down","length":5,"position":{"x":2,"y":0},"solution":"LAWES"},{"id":"4-down","group":["4-down"],"separatorLocations":{},"number":4,"humanNumber":"4","clue":" Typical Woody Allen role","direction":"down","length":9,"position":{"x":3,"y":0},"solution":"INTROVERT"},{"id":"5-down","group":["5-down"],"separatorLocations":{},"number":5,"humanNumber":"5","clue":" North ___, Neb.","direction":"down","length":6,"position":{"x":5,"y":0},"solution":"PLATTE"},{"id":"6-down","group":["6-down"],"separatorLocations":{},"number":6,"humanNumber":"6","clue":" Lithuanians' kin","direction":"down","length":5,"position":{"x":6,"y":0},"solution":"LETTS"},{"id":"7-down","group":["7-down"],"separatorLocations":{},"number":7,"humanNumber":"7","clue":" \"___ Dancer,\" Nureyev film","direction":"down","length":4,"position":{"x":7,"y":0},"solution":"IAMA"},{"id":"8-down","group":["8-down"],"separatorLocations":{},"number":8,"humanNumber":"8","clue":" Age","direction":"down","length":3,"position":{"x":8,"y":0},"solution":"ERA"},{"id":"9-down","group":["9-down"],"separatorLocations":{},"number":9,"humanNumber":"9","clue":" Lottery ticket","direction":"down","length":6,"position":{"x":10,"y":0},"solution":"CHANCE"},{"id":"10-down","group":["10-down"],"separatorLocations":{},"number":10,"humanNumber":"10","clue":" Took life easy","direction":"down","length":6,"position":{"x":11,"y":0},"solution":"RESTED"},{"id":"11-down","group":["11-down"],"separatorLocations":{},"number":11,"humanNumber":"11","clue":" Apportion","direction":"down","length":5,"position":{"x":12,"y":0},"solution":"ALLOT"},{"id":"12-down","group":["12-down"],"separatorLocations":{},"number":12,"humanNumber":"12","clue":" Svelte","direction":"down","length":4,"position":{"x":13,"y":0},"solution":"SLIM"},{"id":"13-down","group":["13-down"],"separatorLocations":{},"number":13,"humanNumber":"13","clue":" Fireplace ledge","direction":"down","length":3,"position":{"x":14,"y":0},"solution":"HOB"},{"id":"14-down","group":["14-down"],"separatorLocations":{},"number":14,"humanNumber":"14","clue":" Dash","direction":"down","length":6,"position":{"x":1,"y":1},"solution":"SPRINT"},{"id":"15-down","group":["15-down"],"separatorLocations":{},"number":15,"humanNumber":"15","clue":" Criterion for a show dog","direction":"down","length":4,"position":{"x":2,"y":1},"solution":"COAT"},{"id":"16-down","group":["16-down"],"separatorLocations":{},"number":16,"humanNumber":"16","clue":" Ionian gulf","direction":"down","length":4,"position":{"x":3,"y":1},"solution":"ARTA"},{"id":"17-down","group":["17-down"],"separatorLocations":{},"number":17,"humanNumber":"17","clue":" Nail remover","direction":"down","length":4,"position":{"x":4,"y":1},"solution":"PEEN"},{"id":"18-down","group":["18-down"],"separatorLocations":{},"number":18,"humanNumber":"18","clue":" Author of \"No and Yes\"","direction":"down","length":4,"position":{"x":5,"y":1},"solution":"EDDY"},{"id":"24-down","group":["24-down"],"separatorLocations":{},"number":24,"humanNumber":"24","clue":" \"From ___ Eternity\"","direction":"down","length":6,"position":{"x":1,"y":3},"solution":"HERETO"},{"id":"25-down","group":["25-down"],"separatorLocations":{},"number":25,"humanNumber":"25","clue":" \"___ Me,\" 1929 song","direction":"down","length":6,"position":{"x":6,"y":3},"solution":"MEANTO"},{"id":"26-down","group":["26-down"],"separatorLocations":{},"number":26,"humanNumber":"26","clue":" Writer Wylie","direction":"down","length":6,"position":{"x":12,"y":3},"solution":"ELINOR"},{"id":"31-down","group":["31-down"],"separatorLocations":{},"number":31,"humanNumber":"31","clue":" Suspect","direction":"down","length":5,"position":{"x":2,"y":6},"solution":"FISHY"},{"id":"32-down","group":["32-down"],"separatorLocations":{},"number":32,"humanNumber":"32","clue":" Scenic peninsula","direction":"down","length":5,"position":{"x":8,"y":6},"solution":"GASPE"},{"id":"34-down","group":["34-down"],"separatorLocations":{},"number":34,"humanNumber":"34","clue":" Korean port","direction":"down","length":5,"position":{"x":7,"y":7},"solution":"PUSAN"},{"id":"35-down","group":["35-down"],"separatorLocations":{},"number":35,"humanNumber":"35","clue":" Irritant","direction":"down","length":5,"position":{"x":13,"y":7},"solution":"THORN"},{"id":"36-down","group":["36-down"],"separatorLocations":{},"number":36,"humanNumber":"36","clue":" Esteem","direction":"down","length":6,"position":{"x":2,"y":8},"solution":"ADMIRE"},{"id":"37-down","group":["37-down"],"separatorLocations":{},"number":37,"humanNumber":"37","clue":" River into Bay of Biscay","direction":"down","length":5,"position":{"x":3,"y":8},"solution":"LOIRE"},{"id":"38-down","group":["38-down"],"separatorLocations":{},"number":38,"humanNumber":"38","clue":" Overthrow","direction":"down","length":5,"position":{"x":4,"y":8},"solution":"UPSET"},{"id":"39-down","group":["39-down"],"separatorLocations":{},"number":39,"humanNumber":"39","clue":" Unkempt","direction":"down","length":5,"position":{"x":5,"y":8},"solution":"SEEDY"},{"id":"40-down","group":["40-down"],"separatorLocations":{},"number":40,"humanNumber":"40","clue":" Batrachian","direction":"down","length":4,"position":{"x":6,"y":8},"solution":"FROG"},{"id":"41-down","group":["41-down"],"separatorLocations":{},"number":41,"humanNumber":"41","clue":" British Open winner: 1964","direction":"down","length":4,"position":{"x":7,"y":8},"solution":"LEMA"},{"id":"42-down","group":["42-down"],"separatorLocations":{},"number":42,"humanNumber":"42","clue":" Rewrite, in a way","direction":"down","length":4,"position":{"x":8,"y":8},"solution":"EDIT"},{"id":"43-down","group":["43-down"],"separatorLocations":{},"number":43,"humanNumber":"43","clue":" Item to be picked","direction":"down","length":5,"position":{"x":12,"y":8},"solution":"BERRY"},{"id":"44-down","group":["44-down"],"separatorLocations":{},"number":44,"humanNumber":"44","clue":" \"The Promised Land\" author","direction":"down","length":5,"position":{"x":3,"y":9},"solution":"ANTIN"},{"id":"47-down","group":["47-down"],"separatorLocations":{},"number":47,"humanNumber":"47","clue":" Teams of horses","direction":"down","length":5,"position":{"x":2,"y":10},"solution":"SPANS"},{"id":"48-down","group":["48-down"],"separatorLocations":{},"number":48,"humanNumber":"48","clue":" Actress Young","direction":"down","length":7,"position":{"x":7,"y":10},"solution":"LORETTA"},{"id":"49-down","group":["49-down"],"separatorLocations":{},"number":49,"humanNumber":"49","clue":" Boxer Bobick","direction":"down","length":5,"position":{"x":8,"y":10},"solution":"DUANE"},{"id":"50-down","group":["50-down"],"separatorLocations":{},"number":50,"humanNumber":"50","clue":" Kyushu port","direction":"down","length":5,"position":{"x":13,"y":10},"solution":"OMUTA"},{"id":"56-down","group":["56-down"],"separatorLocations":{},"number":56,"humanNumber":"56","clue":" Gossip, Yiddish style","direction":"down","length":5,"position":{"x":13,"y":12},"solution":"YENTA"},{"id":"57-down","group":["57-down"],"separatorLocations":{},"number":57,"humanNumber":"57","clue":" Kringle","direction":"down","length":5,"position":{"x":3,"y":13},"solution":"CLAUS"},{"id":"58-down","group":["58-down"],"separatorLocations":{},"number":58,"humanNumber":"58","clue":" Moses' mountain","direction":"down","length":5,"position":{"x":9,"y":13},"solution":"SINAI"},{"id":"59-down","group":["59-down"],"separatorLocations":{},"number":59,"humanNumber":"59","clue":" Far ahead in a golf match","direction":"down","length":6,"position":{"x":3,"y":14},"solution":"DORMIE"},{"id":"60-down","group":["60-down"],"separatorLocations":{},"number":60,"humanNumber":"60","clue":" Revel in a victory","direction":"down","length":5,"position":{"x":8,"y":14},"solution":"GLOAT"},{"id":"61-down","group":["61-down"],"separatorLocations":{},"number":61,"humanNumber":"61","clue":" Swindle or fine","direction":"down","length":5,"position":{"x":14,"y":14},"solution":"MULCT"},{"id":"62-down","group":["62-down"],"separatorLocations":{},"number":62,"humanNumber":"62","clue":" Puzo subject","direction":"down","length":5,"position":{"x":6,"y":15},"solution":"MAFIA"},{"id":"63-down","group":["63-down"],"separatorLocations":{},"number":63,"humanNumber":"63","clue":" Like a loner","direction":"down","length":5,"position":{"x":7,"y":15},"solution":"ALOOF"},{"id":"64-down","group":["64-down"],"separatorLocations":{},"number":64,"humanNumber":"64","clue":" Stroke on a letter","direction":"down","length":5,"position":{"x":8,"y":15},"solution":"SERIF"},{"id":"65-down","group":["65-down"],"separatorLocations":{},"number":65,"humanNumber":"65","clue":" Suffered","direction":"down","length":5,"position":{"x":13,"y":15},"solution":"ACHED"},{"id":"66-down","group":["66-down"],"separatorLocations":{},"number":66,"humanNumber":"66","clue":" Meaning","direction":"down","length":5,"position":{"x":4,"y":16},"solution":"POINT"},{"id":"67-down","group":["67-down"],"separatorLocations":{},"number":67,"humanNumber":"67","clue":" Power unit","direction":"down","length":4,"position":{"x":9,"y":16},"solution":"WATT"},{"id":"68-down","group":["68-down"],"separatorLocations":{},"number":68,"humanNumber":"68","clue":" Columnist Robb","direction":"down","length":4,"position":{"x":10,"y":16},"solution":"INEZ"},{"id":"69-down","group":["69-down"],"separatorLocations":{},"number":69,"humanNumber":"69","clue":" Antimacassar","direction":"down","length":4,"position":{"x":11,"y":16},"solution":"TIDY"},{"id":"71-down","group":["71-down"],"separatorLocations":{},"number":71,"humanNumber":"71","clue":" Cavalry weapon","direction":"down","length":5,"position":{"x":3,"y":17},"solution":"SABER"},{"id":"72-down","group":["72-down"],"separatorLocations":{},"number":72,"humanNumber":"72","clue":" Dwarf","direction":"down","length":5,"position":{"x":9,"y":17},"solution":"STUNT"},{"id":"73-down","group":["73-down"],"separatorLocations":{},"number":73,"humanNumber":"73","clue":" Shower","direction":"down","length":9,"position":{"x":14,"y":17},"solution":"RAINSTORM"},{"id":"75-down","group":["75-down"],"separatorLocations":{},"number":75,"humanNumber":"75","clue":" Develop","direction":"down","length":6,"position":{"x":8,"y":18},"solution":"MATURE"},{"id":"76-down","group":["76-down"],"separatorLocations":{},"number":76,"humanNumber":"76","clue":" Mal de mer","direction":"down","length":6,"position":{"x":14,"y":18},"solution":"NAUSEA"},{"id":"77-down","group":["77-down"],"separatorLocations":{},"number":77,"humanNumber":"77","clue":" Emulate Sunday","direction":"down","length":6,"position":{"x":4,"y":19},"solution":"PREACH"},{"id":"83-down","group":["83-down"],"separatorLocations":{},"number":83,"humanNumber":"83","clue":" String of pearls","direction":"down","length":6,"position":{"x":4,"y":21},"solution":"CHOKER"},{"id":"84-down","group":["84-down"],"separatorLocations":{},"number":84,"humanNumber":"84","clue":" Holland, for one","direction":"down","length":6,"position":{"x":9,"y":21},"solution":"TUNNEL"},{"id":"85-down","group":["85-down"],"separatorLocations":{},"number":85,"humanNumber":"85","clue":" Loser at Palo Alto: 1846","direction":"down","length":6,"position":{"x":10,"y":21},"solution":"ARISTA"},{"id":"86-down","group":["86-down"],"separatorLocations":{},"number":86,"humanNumber":"86","clue":" ___ a pancake","direction":"down","length":6,"position":{"x":0,"y":22},"solution":"FLATAS"},{"id":"88-down","group":["88-down"],"separatorLocations":{},"number":88,"humanNumber":"88","clue":" Turbot","direction":"down","length":5,"position":{"x":14,"y":22},"solution":"BRILL"},{"id":"89-down","group":["89-down"],"separatorLocations":{},"number":89,"humanNumber":"89","clue":" Sinuses","direction":"down","length":5,"position":{"x":5,"y":23},"solution":"ANTRA"},{"id":"90-down","group":["90-down"],"separatorLocations":{},"number":90,"humanNumber":"90","clue":" One of the Lesser Sundas","direction":"down","length":5,"position":{"x":9,"y":23},"solution":"TIMOR"},{"id":"91-down","group":["91-down"],"separatorLocations":{},"number":91,"humanNumber":"91","clue":" Egg-shaped","direction":"down","length":5,"position":{"x":10,"y":23},"solution":"OVATE"},{"id":"92-down","group":["92-down"],"separatorLocations":{},"number":92,"humanNumber":"92","clue":" Doctor a lawn","direction":"down","length":5,"position":{"x":11,"y":23},"solution":"RESOD"},{"id":"93-down","group":["93-down"],"separatorLocations":{},"number":93,"humanNumber":"93","clue":" Found","direction":"down","length":4,"position":{"x":12,"y":23},"solution":"CAST"},{"id":"94-down","group":["94-down"],"separatorLocations":{},"number":94,"humanNumber":"94","clue":" Putting position","direction":"down","length":4,"position":{"x":13,"y":23},"solution":"AWAY"},{"id":"95-down","group":["95-down"],"separatorLocations":{},"number":95,"humanNumber":"95","clue":" Patricia of films","direction":"down","length":4,"position":{"x":14,"y":23},"solution":"NEAL"},{"id":"96-down","group":["96-down"],"separatorLocations":{},"number":96,"humanNumber":"96","clue":" Excise","direction":"down","length":4,"position":{"x":0,"y":24},"solution":"DELE"},{"id":"97-down","group":["97-down"],"separatorLocations":{},"number":97,"humanNumber":"97","clue":" Advantage","direction":"down","length":4,"position":{"x":4,"y":24},"solution":"EDGE"},{"id":"98-down","group":["98-down"],"separatorLocations":{},"number":98,"humanNumber":"98","clue":" Chemical suffix","direction":"down","length":4,"position":{"x":10,"y":24},"solution":"INOL"},{"id":"100-down","group":["100-down"],"separatorLocations":{},"number":100,"humanNumber":"100","clue":" Collar","direction":"down","length":3,"position":{"x":9,"y":25},"solution":"NAB"},{"id":"101-down","group":["101-down"],"separatorLocations":{},"number":101,"humanNumber":"101","clue":" Frost's \"___ Vale\"","direction":"down","length":3,"position":{"x":0,"y":26},"solution":"INA"}],"dimensions":{"cols":21,"rows":21},"crosswordType":"genius"}