{"id":"5/14/1981","name":"1981-05-14","date":"0001-01-01T00:00:00","entries":[{"id":"1-across","group":["1-across"],"separatorLocations":{},"number":1,"humanNumber":"1","clue":" Ayres and Gen. Wallace","direction":"across","length":4,"position":{"x":0,"y":0},"solution":"LEWS"},{"id":"5-across","group":["5-across"],"separatorLocations":{},"number":5,"humanNumber":"5","clue":" Skip over","direction":"across","length":4,"position":{"x":6,"y":0},"solution":"OMIT"},{"id":"9-across","group":["9-across"],"separatorLocations":{},"number":9,"humanNumber":"9","clue":" Scott Joplin's music","direction":"across","length":3,"position":{"x":12,"y":0},"solution":"RAG"},{"id":"12-across","group":["12-across"],"separatorLocations":{},"number":12,"humanNumber":"12","clue":" Mt. Ida maiden of myths","direction":"across","length":5,"position":{"x":0,"y":1},"solution":"OREAD"},{"id":"14-across","group":["14-across"],"separatorLocations":{},"number":14,"humanNumber":"14","clue":" Deadly poison","direction":"across","length":4,"position":{"x":6,"y":1},"solution":"BANE"},{"id":"15-across","group":["15-across"],"separatorLocations":{},"number":15,"humanNumber":"15","clue":" Skylab astronaut: 1973","direction":"across","length":4,"position":{"x":11,"y":1},"solution":"CARR"},{"id":"16-across","group":["16-across"],"separatorLocations":{},"number":16,"humanNumber":"16","clue":" Passageway","direction":"across","length":5,"position":{"x":0,"y":2},"solution":"AISLE"},{"id":"17-across","group":["17-across"],"separatorLocations":{},"number":17,"humanNumber":"17","clue":" Brooklyn–Manhattan divider","direction":"across","length":9,"position":{"x":6,"y":2},"solution":"EASTRIVER"},{"id":"19-across","group":["19-across"],"separatorLocations":{},"number":19,"humanNumber":"19","clue":" Bedding","direction":"across","length":8,"position":{"x":0,"y":3},"solution":"MATTRESS"},{"id":"21-across","group":["21-across"],"separatorLocations":{},"number":21,"humanNumber":"21","clue":" Trojan hero","direction":"across","length":6,"position":{"x":9,"y":3},"solution":"AENEAS"},{"id":"22-across","group":["22-across"],"separatorLocations":{},"number":22,"humanNumber":"22","clue":" Gracie Mansion occupant before Koch","direction":"across","length":5,"position":{"x":2,"y":4},"solution":"BEAME"},{"id":"23-across","group":["23-across"],"separatorLocations":{},"number":23,"humanNumber":"23","clue":" United","direction":"across","length":4,"position":{"x":8,"y":4},"solution":"ONED"},{"id":"24-across","group":["24-across"],"separatorLocations":{},"number":24,"humanNumber":"24","clue":" Tease","direction":"across","length":6,"position":{"x":0,"y":5},"solution":"NEEDLE"},{"id":"26-across","group":["26-across"],"separatorLocations":{},"number":26,"humanNumber":"26","clue":" What Blake called \"a rich, ugly old maid\"","direction":"across","length":8,"position":{"x":7,"y":5},"solution":"PRUDENCE"},{"id":"30-across","group":["30-across"],"separatorLocations":{},"number":30,"humanNumber":"30","clue":" Opposite of lve.","direction":"across","length":3,"position":{"x":0,"y":6},"solution":"ARR"},{"id":"31-across","group":["31-across"],"separatorLocations":{},"number":31,"humanNumber":"31","clue":" Henry VII et al.","direction":"across","length":6,"position":{"x":4,"y":6},"solution":"TUDORS"},{"id":"33-across","group":["33-across"],"separatorLocations":{},"number":33,"humanNumber":"33","clue":" Some marsupials, familiarly","direction":"across","length":4,"position":{"x":11,"y":6},"solution":"ROOS"},{"id":"34-across","group":["34-across"],"separatorLocations":{},"number":34,"humanNumber":"34","clue":" Hull's lowest point","direction":"across","length":5,"position":{"x":0,"y":7},"solution":"BILGE"},{"id":"36-across","group":["36-across"],"separatorLocations":{},"number":36,"humanNumber":"36","clue":" Common Moslem name","direction":"across","length":3,"position":{"x":6,"y":7},"solution":"ALI"},{"id":"37-across","group":["37-across"],"separatorLocations":{},"number":37,"humanNumber":"37","clue":" ___ Raymond Cobb","direction":"across","length":5,"position":{"x":10,"y":7},"solution":"TYRUS"},{"id":"38-across","group":["38-across"],"separatorLocations":{},"number":38,"humanNumber":"38","clue":" Depression migrant","direction":"across","length":4,"position":{"x":0,"y":8},"solution":"OKIE"},{"id":"39-across","group":["39-across"],"separatorLocations":{},"number":39,"humanNumber":"39","clue":" In rapid tempo","direction":"across","length":6,"position":{"x":5,"y":8},"solution":"PRESTO"},{"id":"41-across","group":["41-across"],"separatorLocations":{},"number":41,"humanNumber":"41","clue":" Prefix with foil","direction":"across","length":3,"position":{"x":12,"y":8},"solution":"TRE"},{"id":"42-across","group":["42-across"],"separatorLocations":{},"number":42,"humanNumber":"42","clue":" Ireland's baleful wailers","direction":"across","length":8,"position":{"x":0,"y":9},"solution":"BANSHEES"},{"id":"44-across","group":["44-across"],"separatorLocations":{},"number":44,"humanNumber":"44","clue":" Subjects of 10 amendments","direction":"across","length":6,"position":{"x":9,"y":9},"solution":"RIGHTS"},{"id":"46-across","group":["46-across"],"separatorLocations":{},"number":46,"humanNumber":"46","clue":" Duds","direction":"across","length":4,"position":{"x":3,"y":10},"solution":"TOGS"},{"id":"47-across","group":["47-across"],"separatorLocations":{},"number":47,"humanNumber":"47","clue":" U.S.S.R. or Lebanese statesman","direction":"across","length":5,"position":{"x":8,"y":10},"solution":"MALIK"},{"id":"48-across","group":["48-across"],"separatorLocations":{},"number":48,"humanNumber":"48","clue":" Cornell site","direction":"across","length":6,"position":{"x":0,"y":11},"solution":"ITHACA"},{"id":"51-across","group":["51-across"],"separatorLocations":{},"number":51,"humanNumber":"51","clue":" Bottle encased in wickerwork","direction":"across","length":8,"position":{"x":7,"y":11},"solution":"DEMIJOHN"},{"id":"54-across","group":["54-across"],"separatorLocations":{},"number":54,"humanNumber":"54","clue":" Part of the Pacific","direction":"across","length":9,"position":{"x":0,"y":12},"solution":"SOUTHSEAS"},{"id":"56-across","group":["56-across"],"separatorLocations":{},"number":56,"humanNumber":"56","clue":" Bucketed water wheel","direction":"across","length":5,"position":{"x":10,"y":12},"solution":"NORIA"},{"id":"57-across","group":["57-across"],"separatorLocations":{},"number":57,"humanNumber":"57","clue":" To ___ (exactly)","direction":"across","length":4,"position":{"x":0,"y":13},"solution":"ATEE"},{"id":"58-across","group":["58-across"],"separatorLocations":{},"number":58,"humanNumber":"58","clue":" \"___ the pure all things are pure\"","direction":"across","length":4,"position":{"x":5,"y":13},"solution":"UNTO"},{"id":"59-across","group":["59-across"],"separatorLocations":{},"number":59,"humanNumber":"59","clue":" Simpletons","direction":"across","length":5,"position":{"x":10,"y":13},"solution":"GEESE"},{"id":"60-across","group":["60-across"],"separatorLocations":{},"number":60,"humanNumber":"60","clue":" Word before West or Largo","direction":"across","length":3,"position":{"x":0,"y":14},"solution":"KEY"},{"id":"61-across","group":["61-across"],"separatorLocations":{},"number":61,"humanNumber":"61","clue":" Observed","direction":"across","length":4,"position":{"x":5,"y":14},"solution":"SEEN"},{"id":"62-across","group":["62-across"],"separatorLocations":{},"number":62,"humanNumber":"62","clue":" Back talk","direction":"across","length":4,"position":{"x":11,"y":14},"solution":"SASS"},{"id":"1-down","group":["1-down"],"separatorLocations":{},"number":1,"humanNumber":"1","clue":" Brick mixture","direction":"down","length":4,"position":{"x":0,"y":0},"solution":"LOAM"},{"id":"2-down","group":["2-down"],"separatorLocations":{},"number":2,"humanNumber":"2","clue":" Silkworm","direction":"down","length":4,"position":{"x":1,"y":0},"solution":"ERIA"},{"id":"3-down","group":["3-down"],"separatorLocations":{},"number":3,"humanNumber":"3","clue":" Part of a divided city","direction":"down","length":10,"position":{"x":2,"y":0},"solution":"WESTBERLIN"},{"id":"4-down","group":["4-down"],"separatorLocations":{},"number":4,"humanNumber":"4","clue":" ___ peanuts","direction":"down","length":6,"position":{"x":3,"y":0},"solution":"SALTED"},{"id":"5-down","group":["5-down"],"separatorLocations":{},"number":5,"humanNumber":"5","clue":" Needing a diet","direction":"down","length":5,"position":{"x":6,"y":0},"solution":"OBESE"},{"id":"6-down","group":["6-down"],"separatorLocations":{},"number":6,"humanNumber":"6","clue":" He wrote \"The Valachi Papers\"","direction":"down","length":4,"position":{"x":7,"y":0},"solution":"MAAS"},{"id":"7-down","group":["7-down"],"separatorLocations":{},"number":7,"humanNumber":"7","clue":" Reagan et al.","direction":"down","length":3,"position":{"x":8,"y":0},"solution":"INS"},{"id":"8-down","group":["8-down"],"separatorLocations":{},"number":8,"humanNumber":"8","clue":" Lockjaw","direction":"down","length":7,"position":{"x":9,"y":0},"solution":"TETANUS"},{"id":"9-down","group":["9-down"],"separatorLocations":{},"number":9,"humanNumber":"9","clue":" Type of review","direction":"down","length":4,"position":{"x":12,"y":0},"solution":"RAVE"},{"id":"10-down","group":["10-down"],"separatorLocations":{},"number":10,"humanNumber":"10","clue":" Space","direction":"down","length":4,"position":{"x":13,"y":0},"solution":"AREA"},{"id":"11-down","group":["11-down"],"separatorLocations":{},"number":11,"humanNumber":"11","clue":" Shelties' surly sounds","direction":"down","length":4,"position":{"x":14,"y":0},"solution":"GRRS"},{"id":"13-down","group":["13-down"],"separatorLocations":{},"number":13,"humanNumber":"13","clue":" Adenauer","direction":"down","length":7,"position":{"x":4,"y":1},"solution":"DERALTE"},{"id":"15-down","group":["15-down"],"separatorLocations":{},"number":15,"humanNumber":"15","clue":" Like a well-used fireplace","direction":"down","length":7,"position":{"x":11,"y":1},"solution":"CINDERY"},{"id":"18-down","group":["18-down"],"separatorLocations":{},"number":18,"humanNumber":"18","clue":" Donna or Rex","direction":"down","length":4,"position":{"x":10,"y":2},"solution":"REED"},{"id":"20-down","group":["20-down"],"separatorLocations":{},"number":20,"humanNumber":"20","clue":" Flightless bird","direction":"down","length":4,"position":{"x":5,"y":3},"solution":"EMEU"},{"id":"23-down","group":["23-down"],"separatorLocations":{},"number":23,"humanNumber":"23","clue":" Oil used in perfumes","direction":"down","length":5,"position":{"x":8,"y":4},"solution":"ORRIS"},{"id":"24-down","group":["24-down"],"separatorLocations":{},"number":24,"humanNumber":"24","clue":" Big shot","direction":"down","length":5,"position":{"x":0,"y":5},"solution":"NABOB"},{"id":"25-down","group":["25-down"],"separatorLocations":{},"number":25,"humanNumber":"25","clue":" Violinist Morini","direction":"down","length":5,"position":{"x":1,"y":5},"solution":"ERIKA"},{"id":"26-down","group":["26-down"],"separatorLocations":{},"number":26,"humanNumber":"26","clue":" Vaulting equipment","direction":"down","length":5,"position":{"x":7,"y":5},"solution":"POLES"},{"id":"27-down","group":["27-down"],"separatorLocations":{},"number":27,"humanNumber":"27","clue":" Pyongyang is its capital","direction":"down","length":10,"position":{"x":12,"y":5},"solution":"NORTHKOREA"},{"id":"28-down","group":["28-down"],"separatorLocations":{},"number":28,"humanNumber":"28","clue":" Woo","direction":"down","length":5,"position":{"x":13,"y":5},"solution":"COURT"},{"id":"29-down","group":["29-down"],"separatorLocations":{},"number":29,"humanNumber":"29","clue":" Letters","direction":"down","length":5,"position":{"x":14,"y":5},"solution":"ESSES"},{"id":"32-down","group":["32-down"],"separatorLocations":{},"number":32,"humanNumber":"32","clue":" Challenges","direction":"down","length":5,"position":{"x":6,"y":6},"solution":"DARES"},{"id":"35-down","group":["35-down"],"separatorLocations":{},"number":35,"humanNumber":"35","clue":" Conceive and gradually develop","direction":"down","length":7,"position":{"x":3,"y":7},"solution":"GESTATE"},{"id":"37-down","group":["37-down"],"separatorLocations":{},"number":37,"humanNumber":"37","clue":" Peon's lot","direction":"down","length":7,"position":{"x":10,"y":7},"solution":"TOILING"},{"id":"39-down","group":["39-down"],"separatorLocations":{},"number":39,"humanNumber":"39","clue":" Winged steed","direction":"down","length":7,"position":{"x":5,"y":8},"solution":"PEGASUS"},{"id":"40-down","group":["40-down"],"separatorLocations":{},"number":40,"humanNumber":"40","clue":" Cable car","direction":"down","length":4,"position":{"x":9,"y":8},"solution":"TRAM"},{"id":"43-down","group":["43-down"],"separatorLocations":{},"number":43,"humanNumber":"43","clue":" Lofty, in Leipzig","direction":"down","length":4,"position":{"x":4,"y":9},"solution":"HOCH"},{"id":"45-down","group":["45-down"],"separatorLocations":{},"number":45,"humanNumber":"45","clue":" Doughboys of W.W. II","direction":"down","length":6,"position":{"x":11,"y":9},"solution":"GIJOES"},{"id":"47-down","group":["47-down"],"separatorLocations":{},"number":47,"humanNumber":"47","clue":" Subatomic particle","direction":"down","length":5,"position":{"x":8,"y":10},"solution":"MESON"},{"id":"48-down","group":["48-down"],"separatorLocations":{},"number":48,"humanNumber":"48","clue":" Author Dinesen","direction":"down","length":4,"position":{"x":0,"y":11},"solution":"ISAK"},{"id":"49-down","group":["49-down"],"separatorLocations":{},"number":49,"humanNumber":"49","clue":" Word with bag or board","direction":"down","length":4,"position":{"x":1,"y":11},"solution":"TOTE"},{"id":"50-down","group":["50-down"],"separatorLocations":{},"number":50,"humanNumber":"50","clue":" One of the Longs","direction":"down","length":4,"position":{"x":2,"y":11},"solution":"HUEY"},{"id":"51-down","group":["51-down"],"separatorLocations":{},"number":51,"humanNumber":"51","clue":" Oct. 12, 1492, e.g.","direction":"down","length":4,"position":{"x":7,"y":11},"solution":"DATE"},{"id":"52-down","group":["52-down"],"separatorLocations":{},"number":52,"humanNumber":"52","clue":" Derisive sound","direction":"down","length":4,"position":{"x":13,"y":11},"solution":"HISS"},{"id":"53-down","group":["53-down"],"separatorLocations":{},"number":53,"humanNumber":"53","clue":" Denials in Glasgow","direction":"down","length":4,"position":{"x":14,"y":11},"solution":"NAES"},{"id":"55-down","group":["55-down"],"separatorLocations":{},"number":55,"humanNumber":"55","clue":" Weathercock indication","direction":"down","length":3,"position":{"x":6,"y":12},"solution":"ENE"}],"dimensions":{"cols":15,"rows":15},"crosswordType":"genius"}