{"id":"11/5/1989","name":"1989-11-05","date":"0001-01-01T00:00:00","entries":[{"id":"1-across","group":["1-across"],"separatorLocations":{},"number":1,"humanNumber":"1","clue":" Reeking","direction":"across","length":4,"position":{"x":0,"y":0},"solution":"OLID"},{"id":"5-across","group":["5-across"],"separatorLocations":{},"number":5,"humanNumber":"5","clue":" Surly","direction":"across","length":5,"position":{"x":5,"y":0},"solution":"GRUFF"},{"id":"10-across","group":["10-across"],"separatorLocations":{},"number":10,"humanNumber":"10","clue":" Cote sound","direction":"across","length":3,"position":{"x":12,"y":0},"solution":"COO"},{"id":"13-across","group":["13-across"],"separatorLocations":{},"number":13,"humanNumber":"13","clue":" Abominated","direction":"across","length":5,"position":{"x":1,"y":1},"solution":"HATED"},{"id":"18-across","group":["18-across"],"separatorLocations":{},"number":18,"humanNumber":"18","clue":" ___ Nostra","direction":"across","length":4,"position":{"x":6,"y":1},"solution":"COSA"},{"id":"19-across","group":["19-across"],"separatorLocations":{},"number":19,"humanNumber":"19","clue":" A hundred paise","direction":"across","length":5,"position":{"x":11,"y":1},"solution":"RUPEE"},{"id":"20-across","group":["20-across"],"separatorLocations":{},"number":20,"humanNumber":"20","clue":" ___ food","direction":"across","length":4,"position":{"x":2,"y":2},"solution":"SOUL"},{"id":"21-across","group":["21-across"],"separatorLocations":{},"number":21,"humanNumber":"21","clue":" Sadat","direction":"across","length":5,"position":{"x":7,"y":2},"solution":"ANWAR"},{"id":"22-across","group":["22-across"],"separatorLocations":{},"number":22,"humanNumber":"22","clue":" Charlemagne (800)–Francis II (1806)","direction":"across","length":15,"position":{"x":12,"y":2},"solution":"HOLYROMANEMPIRE"},{"id":"25-across","group":["25-across"],"separatorLocations":{},"number":25,"humanNumber":"25","clue":" Lovelace's forte","direction":"across","length":5,"position":{"x":13,"y":3},"solution":"POESY"},{"id":"26-across","group":["26-across"],"separatorLocations":{},"number":26,"humanNumber":"26","clue":" Stages in lives of organisms","direction":"across","length":8,"position":{"x":3,"y":4},"solution":"STADIUMS"},{"id":"27-across","group":["27-across"],"separatorLocations":{},"number":27,"humanNumber":"27","clue":" Legal claims","direction":"across","length":5,"position":{"x":12,"y":4},"solution":"LIENS"},{"id":"28-across","group":["28-across"],"separatorLocations":{},"number":28,"humanNumber":"28","clue":" Parts of books","direction":"across","length":6,"position":{"x":3,"y":5},"solution":"SPINES"},{"id":"29-across","group":["29-across"],"separatorLocations":{},"number":29,"humanNumber":"29","clue":" Viscid","direction":"across","length":4,"position":{"x":12,"y":5},"solution":"ROPY"},{"id":"30-across","group":["30-across"],"separatorLocations":{},"number":30,"humanNumber":"30","clue":" Eucharist containers: Var.","direction":"across","length":5,"position":{"x":2,"y":6},"solution":"PIXES"},{"id":"31-across","group":["31-across"],"separatorLocations":{},"number":31,"humanNumber":"31","clue":" Faint appearance","direction":"across","length":5,"position":{"x":8,"y":6},"solution":"GLINT"},{"id":"32-across","group":["32-across"],"separatorLocations":{},"number":32,"humanNumber":"32","clue":" Early French monarchs","direction":"across","length":6,"position":{"x":0,"y":7},"solution":"CAPETS"},{"id":"35-across","group":["35-across"],"separatorLocations":{},"number":35,"humanNumber":"35","clue":" Ate elegantly","direction":"across","length":5,"position":{"x":7,"y":7},"solution":"DINED"},{"id":"36-across","group":["36-across"],"separatorLocations":{},"number":36,"humanNumber":"36","clue":" Loyalties","direction":"across","length":8,"position":{"x":13,"y":7},"solution":"FEALTIES"},{"id":"39-across","group":["39-across"],"separatorLocations":{},"number":39,"humanNumber":"39","clue":" Wahines' dances","direction":"across","length":5,"position":{"x":6,"y":8},"solution":"HULAS"},{"id":"40-across","group":["40-across"],"separatorLocations":{},"number":40,"humanNumber":"40","clue":" T'ai Tsu (1368)–Chuang-lieh-ti (1644)","direction":"across","length":11,"position":{"x":12,"y":8},"solution":"MINGDYNASTY"},{"id":"42-across","group":["42-across"],"separatorLocations":{},"number":42,"humanNumber":"42","clue":" Wawaskeesh","direction":"across","length":3,"position":{"x":9,"y":9},"solution":"ELK"},{"id":"43-across","group":["43-across"],"separatorLocations":{},"number":43,"humanNumber":"43","clue":" Agenda unit","direction":"across","length":4,"position":{"x":12,"y":9},"solution":"ITEM"},{"id":"44-across","group":["44-across"],"separatorLocations":{},"number":44,"humanNumber":"44","clue":" His name means \"I am faithful\"","direction":"across","length":4,"position":{"x":2,"y":10},"solution":"FIDO"},{"id":"45-across","group":["45-across"],"separatorLocations":{},"number":45,"humanNumber":"45","clue":" Grafted: Her.","direction":"across","length":4,"position":{"x":9,"y":10},"solution":"ENTE"},{"id":"46-across","group":["46-across"],"separatorLocations":{},"number":46,"humanNumber":"46","clue":" Norman town","direction":"across","length":4,"position":{"x":14,"y":10},"solution":"STLO"},{"id":"47-across","group":["47-across"],"separatorLocations":{},"number":47,"humanNumber":"47","clue":" Miss Piggy's pronoun","direction":"across","length":3,"position":{"x":3,"y":11},"solution":"MOI"},{"id":"48-across","group":["48-across"],"separatorLocations":{},"number":48,"humanNumber":"48","clue":" Paleolithic period","direction":"across","length":11,"position":{"x":7,"y":11},"solution":"OLDSTONEAGE"},{"id":"52-across","group":["52-across"],"separatorLocations":{},"number":52,"humanNumber":"52","clue":" Brazilian state","direction":"across","length":5,"position":{"x":4,"y":12},"solution":"BAHIA"},{"id":"53-across","group":["53-across"],"separatorLocations":{},"number":53,"humanNumber":"53","clue":" Lamb or Bacon","direction":"across","length":8,"position":{"x":9,"y":12},"solution":"ESSAYIST"},{"id":"55-across","group":["55-across"],"separatorLocations":{},"number":55,"humanNumber":"55","clue":" Staggers","direction":"across","length":5,"position":{"x":3,"y":13},"solution":"REELS"},{"id":"56-across","group":["56-across"],"separatorLocations":{},"number":56,"humanNumber":"56","clue":" Neutralize","direction":"across","length":6,"position":{"x":9,"y":13},"solution":"CANCEL"},{"id":"57-across","group":["57-across"],"separatorLocations":{},"number":57,"humanNumber":"57","clue":" Chirp","direction":"across","length":5,"position":{"x":2,"y":14},"solution":"TWEET"},{"id":"58-across","group":["58-across"],"separatorLocations":{},"number":58,"humanNumber":"58","clue":" Runs away","direction":"across","length":5,"position":{"x":8,"y":14},"solution":"FLEES"},{"id":"59-across","group":["59-across"],"separatorLocations":{},"number":59,"humanNumber":"59","clue":" \"___ d'Arthur\": Tennyson","direction":"across","length":5,"position":{"x":14,"y":14},"solution":"MORTE"},{"id":"60-across","group":["60-across"],"separatorLocations":{},"number":60,"humanNumber":"60","clue":" Animal tracks","direction":"across","length":6,"position":{"x":6,"y":15},"solution":"SPOORS"},{"id":"62-across","group":["62-across"],"separatorLocations":{},"number":62,"humanNumber":"62","clue":" Eat away","direction":"across","length":5,"position":{"x":13,"y":15},"solution":"ERODE"},{"id":"63-across","group":["63-across"],"separatorLocations":{},"number":63,"humanNumber":"63","clue":" Changes sugar to alcohol","direction":"across","length":8,"position":{"x":4,"y":16},"solution":"FERMENTS"},{"id":"66-across","group":["66-across"],"separatorLocations":{},"number":66,"humanNumber":"66","clue":" Gripes","direction":"across","length":5,"position":{"x":12,"y":16},"solution":"KICKS"},{"id":"67-across","group":["67-across"],"separatorLocations":{},"number":67,"humanNumber":"67","clue":" February 29","direction":"across","length":11,"position":{"x":3,"y":17},"solution":"LEAPYEARDAY"},{"id":"69-across","group":["69-across"],"separatorLocations":{},"number":69,"humanNumber":"69","clue":" Gumshoe","direction":"across","length":3,"position":{"x":0,"y":18},"solution":"TEC"},{"id":"70-across","group":["70-across"],"separatorLocations":{},"number":70,"humanNumber":"70","clue":" Arrow poison","direction":"across","length":4,"position":{"x":3,"y":18},"solution":"INEE"},{"id":"71-across","group":["71-across"],"separatorLocations":{},"number":71,"humanNumber":"71","clue":" Tale","direction":"across","length":4,"position":{"x":8,"y":18},"solution":"YARN"},{"id":"72-across","group":["72-across"],"separatorLocations":{},"number":72,"humanNumber":"72","clue":" Tenor Shicoff","direction":"across","length":4,"position":{"x":0,"y":19},"solution":"NEIL"},{"id":"73-across","group":["73-across"],"separatorLocations":{},"number":73,"humanNumber":"73","clue":" Whine","direction":"across","length":4,"position":{"x":5,"y":19},"solution":"PULE"},{"id":"74-across","group":["74-across"],"separatorLocations":{},"number":74,"humanNumber":"74","clue":" Eliot's \"The Hollow ___\"","direction":"across","length":3,"position":{"x":9,"y":19},"solution":"MEN"},{"id":"75-across","group":["75-across"],"separatorLocations":{},"number":75,"humanNumber":"75","clue":" When dinosaurs roamed the earth","direction":"across","length":11,"position":{"x":13,"y":19},"solution":"MESOZOICERA"},{"id":"79-across","group":["79-across"],"separatorLocations":{},"number":79,"humanNumber":"79","clue":" Firth of Clyde island","direction":"across","length":5,"position":{"x":10,"y":20},"solution":"ARRAN"},{"id":"80-across","group":["80-across"],"separatorLocations":{},"number":80,"humanNumber":"80","clue":" Supposes","direction":"across","length":8,"position":{"x":0,"y":21},"solution":"PRESUMES"},{"id":"82-across","group":["82-across"],"separatorLocations":{},"number":82,"humanNumber":"82","clue":" Fatuous","direction":"across","length":5,"position":{"x":9,"y":21},"solution":"INANE"},{"id":"83-across","group":["83-across"],"separatorLocations":{},"number":83,"humanNumber":"83","clue":" Made raids for booty","direction":"across","length":6,"position":{"x":0,"y":22},"solution":"PREYED"},{"id":"84-across","group":["84-across"],"separatorLocations":{},"number":84,"humanNumber":"84","clue":" \"The Pumpkin ___,\" 1964 film","direction":"across","length":5,"position":{"x":8,"y":22},"solution":"EATER"},{"id":"85-across","group":["85-across"],"separatorLocations":{},"number":85,"humanNumber":"85","clue":" Coquette","direction":"across","length":5,"position":{"x":14,"y":22},"solution":"FLIRT"},{"id":"86-across","group":["86-across"],"separatorLocations":{},"number":86,"humanNumber":"86","clue":" Samoyeds and schipperkes","direction":"across","length":4,"position":{"x":5,"y":23},"solution":"DOGS"},{"id":"87-across","group":["87-across"],"separatorLocations":{},"number":87,"humanNumber":"87","clue":" ___ Zee Bridge, N.Y.","direction":"across","length":6,"position":{"x":12,"y":23},"solution":"TAPPAN"},{"id":"89-across","group":["89-across"],"separatorLocations":{},"number":89,"humanNumber":"89","clue":" City on the Meuse","direction":"across","length":5,"position":{"x":4,"y":24},"solution":"LIEGE"},{"id":"90-across","group":["90-across"],"separatorLocations":{},"number":90,"humanNumber":"90","clue":" Located","direction":"across","length":8,"position":{"x":10,"y":24},"solution":"SITUATED"},{"id":"94-across","group":["94-across"],"separatorLocations":{},"number":94,"humanNumber":"94","clue":" Not give ___ (be unconcerned)","direction":"across","length":5,"position":{"x":3,"y":25},"solution":"AHOOT"},{"id":"95-across","group":["95-across"],"separatorLocations":{},"number":95,"humanNumber":"95","clue":" A.H. 1 or A.D. 622","direction":"across","length":15,"position":{"x":9,"y":25},"solution":"YEAROFTHEHEGIRA"},{"id":"97-across","group":["97-across"],"separatorLocations":{},"number":97,"humanNumber":"97","clue":" Mother-of-pearl","direction":"across","length":5,"position":{"x":9,"y":26},"solution":"NACRE"},{"id":"98-across","group":["98-across"],"separatorLocations":{},"number":98,"humanNumber":"98","clue":" Pangolin's feast","direction":"across","length":4,"position":{"x":0,"y":27},"solution":"ANTS"},{"id":"99-across","group":["99-across"],"separatorLocations":{},"number":99,"humanNumber":"99","clue":" Like a Cheviot","direction":"across","length":5,"position":{"x":5,"y":27},"solution":"OVINE"},{"id":"100-across","group":["100-across"],"separatorLocations":{},"number":100,"humanNumber":"100","clue":" Innisfail","direction":"across","length":4,"position":{"x":11,"y":27},"solution":"ERIN"},{"id":"101-across","group":["101-across"],"separatorLocations":{},"number":101,"humanNumber":"101","clue":" Oleaceous trees","direction":"across","length":5,"position":{"x":0,"y":28},"solution":"ASHES"},{"id":"102-across","group":["102-across"],"separatorLocations":{},"number":102,"humanNumber":"102","clue":" What, in Weimar","direction":"across","length":3,"position":{"x":6,"y":28},"solution":"WAS"},{"id":"103-across","group":["103-across"],"separatorLocations":{},"number":103,"humanNumber":"103","clue":" Delirious one","direction":"across","length":5,"position":{"x":11,"y":28},"solution":"RAVER"},{"id":"104-across","group":["104-across"],"separatorLocations":{},"number":104,"humanNumber":"104","clue":" Knock down in the ring","direction":"across","length":4,"position":{"x":2,"y":29},"solution":"DECK"},{"id":"1-down","group":["1-down"],"separatorLocations":{},"number":1,"humanNumber":"1","clue":" Noted newspaper publisher","direction":"down","length":4,"position":{"x":0,"y":0},"solution":"OCHS"},{"id":"2-down","group":["2-down"],"separatorLocations":{},"number":2,"humanNumber":"2","clue":" Terhune novel","direction":"down","length":4,"position":{"x":1,"y":0},"solution":"LOOT"},{"id":"3-down","group":["3-down"],"separatorLocations":{},"number":3,"humanNumber":"3","clue":" Cuba, e.g.","direction":"down","length":4,"position":{"x":2,"y":0},"solution":"ISLA"},{"id":"4-down","group":["4-down"],"separatorLocations":{},"number":4,"humanNumber":"4","clue":" Reverie","direction":"down","length":8,"position":{"x":3,"y":0},"solution":"DAYDREAM"},{"id":"5-down","group":["5-down"],"separatorLocations":{},"number":5,"humanNumber":"5","clue":" Assemblages","direction":"down","length":6,"position":{"x":5,"y":0},"solution":"GROUPS"},{"id":"6-down","group":["6-down"],"separatorLocations":{},"number":6,"humanNumber":"6","clue":" Card game","direction":"down","length":5,"position":{"x":6,"y":0},"solution":"RUMMY"},{"id":"7-down","group":["7-down"],"separatorLocations":{},"number":7,"humanNumber":"7","clue":" Asian evergreen","direction":"down","length":4,"position":{"x":7,"y":0},"solution":"UPAS"},{"id":"8-down","group":["8-down"],"separatorLocations":{},"number":8,"humanNumber":"8","clue":" Bog","direction":"down","length":3,"position":{"x":8,"y":0},"solution":"FEN"},{"id":"9-down","group":["9-down"],"separatorLocations":{},"number":9,"humanNumber":"9","clue":" Sensitivity","direction":"down","length":7,"position":{"x":9,"y":0},"solution":"FEELING"},{"id":"10-down","group":["10-down"],"separatorLocations":{},"number":10,"humanNumber":"10","clue":" Numismatist's concern","direction":"down","length":5,"position":{"x":12,"y":0},"solution":"COINS"},{"id":"11-down","group":["11-down"],"separatorLocations":{},"number":11,"humanNumber":"11","clue":" Possessive pronoun","direction":"down","length":4,"position":{"x":13,"y":0},"solution":"OURS"},{"id":"12-down","group":["12-down"],"separatorLocations":{},"number":12,"humanNumber":"12","clue":" Violinist Bull","direction":"down","length":3,"position":{"x":14,"y":0},"solution":"OLE"},{"id":"13-down","group":["13-down"],"separatorLocations":{},"number":13,"humanNumber":"13","clue":" With pleasure","direction":"down","length":7,"position":{"x":1,"y":1},"solution":"HAPPILY"},{"id":"14-down","group":["14-down"],"separatorLocations":{},"number":14,"humanNumber":"14","clue":" Consecrate by unction","direction":"down","length":6,"position":{"x":2,"y":1},"solution":"ANOINT"},{"id":"15-down","group":["15-down"],"separatorLocations":{},"number":15,"humanNumber":"15","clue":" Today, in a way","direction":"down","length":16,"position":{"x":3,"y":1},"solution":"TWENTIETHCENTURY"},{"id":"16-down","group":["16-down"],"separatorLocations":{},"number":16,"humanNumber":"16","clue":" Tranquillity","direction":"down","length":4,"position":{"x":4,"y":1},"solution":"EASE"},{"id":"17-down","group":["17-down"],"separatorLocations":{},"number":17,"humanNumber":"17","clue":" Prohibitionists","direction":"down","length":4,"position":{"x":5,"y":1},"solution":"DRYS"},{"id":"20-down","group":["20-down"],"separatorLocations":{},"number":20,"humanNumber":"20","clue":" Like Gonzales of songdom","direction":"down","length":6,"position":{"x":2,"y":2},"solution":"SPEEDY"},{"id":"23-down","group":["23-down"],"separatorLocations":{},"number":23,"humanNumber":"23","clue":" Very funny fellows","direction":"down","length":5,"position":{"x":1,"y":3},"solution":"RIOTS"},{"id":"24-down","group":["24-down"],"separatorLocations":{},"number":24,"humanNumber":"24","clue":" Kind of doubles","direction":"down","length":5,"position":{"x":7,"y":3},"solution":"MIXED"},{"id":"28-down","group":["28-down"],"separatorLocations":{},"number":28,"humanNumber":"28","clue":" Shade of gray","direction":"down","length":5,"position":{"x":3,"y":5},"solution":"SLATE"},{"id":"30-down","group":["30-down"],"separatorLocations":{},"number":30,"humanNumber":"30","clue":" Grape variety","direction":"down","length":5,"position":{"x":2,"y":6},"solution":"PINOT"},{"id":"31-down","group":["31-down"],"separatorLocations":{},"number":31,"humanNumber":"31","clue":" \"Beau ___,\" Wren work","direction":"down","length":5,"position":{"x":8,"y":6},"solution":"GESTE"},{"id":"32-down","group":["32-down"],"separatorLocations":{},"number":32,"humanNumber":"32","clue":" Edge of a cask","direction":"down","length":5,"position":{"x":0,"y":7},"solution":"CHIME"},{"id":"33-down","group":["33-down"],"separatorLocations":{},"number":33,"humanNumber":"33","clue":" Auburn and Marmon","direction":"down","length":5,"position":{"x":1,"y":7},"solution":"AUTOS"},{"id":"34-down","group":["34-down"],"separatorLocations":{},"number":34,"humanNumber":"34","clue":" Ice Age","direction":"down","length":16,"position":{"x":2,"y":7},"solution":"PLEISTOCENEEPOCH"},{"id":"35-down","group":["35-down"],"separatorLocations":{},"number":35,"humanNumber":"35","clue":" \"When thou ___ terrible things\": Isa. 64:3","direction":"down","length":5,"position":{"x":7,"y":7},"solution":"DIDST"},{"id":"36-down","group":["36-down"],"separatorLocations":{},"number":36,"humanNumber":"36","clue":" Adder's armament","direction":"down","length":5,"position":{"x":13,"y":7},"solution":"FANGS"},{"id":"37-down","group":["37-down"],"separatorLocations":{},"number":37,"humanNumber":"37","clue":" \"___ Rhee,\" Civil War song","direction":"down","length":5,"position":{"x":4,"y":8},"solution":"ELLIE"},{"id":"38-down","group":["38-down"],"separatorLocations":{},"number":38,"humanNumber":"38","clue":" Kin of 46 Down","direction":"down","length":5,"position":{"x":5,"y":8},"solution":"SKOAL"},{"id":"40-down","group":["40-down"],"separatorLocations":{},"number":40,"humanNumber":"40","clue":" Center","direction":"down","length":5,"position":{"x":12,"y":8},"solution":"MIDST"},{"id":"41-down","group":["41-down"],"separatorLocations":{},"number":41,"humanNumber":"41","clue":" Patricia and Tom of films","direction":"down","length":5,"position":{"x":3,"y":9},"solution":"NEALS"},{"id":"44-down","group":["44-down"],"separatorLocations":{},"number":44,"humanNumber":"44","clue":" What time does","direction":"down","length":5,"position":{"x":2,"y":10},"solution":"FLIES"},{"id":"46-down","group":["46-down"],"separatorLocations":{},"number":46,"humanNumber":"46","clue":" A votre ___! (Cheers!)","direction":"down","length":5,"position":{"x":14,"y":10},"solution":"SANTE"},{"id":"48-down","group":["48-down"],"separatorLocations":{},"number":48,"humanNumber":"48","clue":" Court hearings","direction":"down","length":5,"position":{"x":7,"y":11},"solution":"OYERS"},{"id":"49-down","group":["49-down"],"separatorLocations":{},"number":49,"humanNumber":"49","clue":" Ship's lowest deck","direction":"down","length":5,"position":{"x":12,"y":11},"solution":"ORLOP"},{"id":"50-down","group":["50-down"],"separatorLocations":{},"number":50,"humanNumber":"50","clue":" Indigent","direction":"down","length":5,"position":{"x":13,"y":11},"solution":"NEEDY"},{"id":"51-down","group":["51-down"],"separatorLocations":{},"number":51,"humanNumber":"51","clue":" Size for Bigfoot or Yeti?","direction":"down","length":5,"position":{"x":14,"y":11},"solution":"EEEEE"},{"id":"52-down","group":["52-down"],"separatorLocations":{},"number":52,"humanNumber":"52","clue":" Full of froth","direction":"down","length":5,"position":{"x":4,"y":12},"solution":"BARMY"},{"id":"54-down","group":["54-down"],"separatorLocations":{},"number":54,"humanNumber":"54","clue":" Left Nod","direction":"down","length":5,"position":{"x":12,"y":12},"solution":"AWOKE"},{"id":"56-down","group":["56-down"],"separatorLocations":{},"number":56,"humanNumber":"56","clue":" Staghorn","direction":"down","length":5,"position":{"x":9,"y":13},"solution":"CORAL"},{"id":"58-down","group":["58-down"],"separatorLocations":{},"number":58,"humanNumber":"58","clue":" Lehár or Schubert","direction":"down","length":5,"position":{"x":8,"y":14},"solution":"FRANZ"},{"id":"59-down","group":["59-down"],"separatorLocations":{},"number":59,"humanNumber":"59","clue":" Radio and TV","direction":"down","length":5,"position":{"x":14,"y":14},"solution":"MEDIA"},{"id":"60-down","group":["60-down"],"separatorLocations":{},"number":60,"humanNumber":"60","clue":" Be miserly","direction":"down","length":5,"position":{"x":6,"y":15},"solution":"SKIMP"},{"id":"61-down","group":["61-down"],"separatorLocations":{},"number":61,"humanNumber":"61","clue":" Anguished one","direction":"down","length":5,"position":{"x":7,"y":15},"solution":"PINER"},{"id":"62-down","group":["62-down"],"separatorLocations":{},"number":62,"humanNumber":"62","clue":" Saarinen's namesakes","direction":"down","length":5,"position":{"x":13,"y":15},"solution":"EEROS"},{"id":"63-down","group":["63-down"],"separatorLocations":{},"number":63,"humanNumber":"63","clue":" Jacques's title in song","direction":"down","length":5,"position":{"x":4,"y":16},"solution":"FRERE"},{"id":"64-down","group":["64-down"],"separatorLocations":{},"number":64,"humanNumber":"64","clue":" Anatomical tissues","direction":"down","length":5,"position":{"x":10,"y":16},"solution":"TELAE"},{"id":"65-down","group":["65-down"],"separatorLocations":{},"number":65,"humanNumber":"65","clue":" Rise on a wave","direction":"down","length":5,"position":{"x":11,"y":16},"solution":"SCEND"},{"id":"67-down","group":["67-down"],"separatorLocations":{},"number":67,"humanNumber":"67","clue":" Device used in microsurgery","direction":"down","length":5,"position":{"x":3,"y":17},"solution":"LASER"},{"id":"68-down","group":["68-down"],"separatorLocations":{},"number":68,"humanNumber":"68","clue":" Concerning","direction":"down","length":5,"position":{"x":9,"y":17},"solution":"ANENT"},{"id":"71-down","group":["71-down"],"separatorLocations":{},"number":71,"humanNumber":"71","clue":" Red Sea republic","direction":"down","length":5,"position":{"x":8,"y":18},"solution":"YEMEN"},{"id":"73-down","group":["73-down"],"separatorLocations":{},"number":73,"humanNumber":"73","clue":" Foretold","direction":"down","length":8,"position":{"x":5,"y":19},"solution":"PRESAGED"},{"id":"75-down","group":["75-down"],"separatorLocations":{},"number":75,"humanNumber":"75","clue":" Changes genetically","direction":"down","length":7,"position":{"x":13,"y":19},"solution":"MUTATES"},{"id":"76-down","group":["76-down"],"separatorLocations":{},"number":76,"humanNumber":"76","clue":" Houston eleven","direction":"down","length":6,"position":{"x":3,"y":20},"solution":"OILERS"},{"id":"77-down","group":["77-down"],"separatorLocations":{},"number":77,"humanNumber":"77","clue":" Architect Jones","direction":"down","length":5,"position":{"x":4,"y":20},"solution":"INIGO"},{"id":"78-down","group":["78-down"],"separatorLocations":{},"number":78,"humanNumber":"78","clue":" Like","direction":"down","length":7,"position":{"x":5,"y":20},"solution":"CAREFOR"},{"id":"79-down","group":["79-down"],"separatorLocations":{},"number":79,"humanNumber":"79","clue":" Debate","direction":"down","length":5,"position":{"x":10,"y":20},"solution":"ARGUE"},{"id":"81-down","group":["81-down"],"separatorLocations":{},"number":81,"humanNumber":"81","clue":" Flavor, in Ferrara","direction":"down","length":6,"position":{"x":3,"y":21},"solution":"SAPORE"},{"id":"83-down","group":["83-down"],"separatorLocations":{},"number":83,"humanNumber":"83","clue":" Bustle; confusion","direction":"down","length":6,"position":{"x":0,"y":22},"solution":"POTHER"},{"id":"85-down","group":["85-down"],"separatorLocations":{},"number":85,"humanNumber":"85","clue":" Edicts","direction":"down","length":5,"position":{"x":14,"y":22},"solution":"FIATS"},{"id":"86-down","group":["86-down"],"separatorLocations":{},"number":86,"humanNumber":"86","clue":" Chemical compound","direction":"down","length":5,"position":{"x":5,"y":23},"solution":"DIENE"},{"id":"87-down","group":["87-down"],"separatorLocations":{},"number":87,"humanNumber":"87","clue":" Lake ___, source of the Blue Nile","direction":"down","length":4,"position":{"x":12,"y":23},"solution":"TANA"},{"id":"88-down","group":["88-down"],"separatorLocations":{},"number":88,"humanNumber":"88","clue":" Cries of discovery","direction":"down","length":4,"position":{"x":13,"y":23},"solution":"AHAS"},{"id":"89-down","group":["89-down"],"separatorLocations":{},"number":89,"humanNumber":"89","clue":" Irkutsk river","direction":"down","length":4,"position":{"x":4,"y":24},"solution":"LENA"},{"id":"90-down","group":["90-down"],"separatorLocations":{},"number":90,"humanNumber":"90","clue":" Hood's blade","direction":"down","length":4,"position":{"x":10,"y":24},"solution":"SHIV"},{"id":"91-down","group":["91-down"],"separatorLocations":{},"number":91,"humanNumber":"91","clue":" Flag","direction":"down","length":4,"position":{"x":0,"y":25},"solution":"TIRE"},{"id":"92-down","group":["92-down"],"separatorLocations":{},"number":92,"humanNumber":"92","clue":" ___ Blair (George Orwell)","direction":"down","length":4,"position":{"x":1,"y":25},"solution":"ERIC"},{"id":"93-down","group":["93-down"],"separatorLocations":{},"number":93,"humanNumber":"93","clue":" Moist and chilly","direction":"down","length":4,"position":{"x":2,"y":25},"solution":"DANK"},{"id":"95-down","group":["95-down"],"separatorLocations":{},"number":95,"humanNumber":"95","clue":" Deviate from course","direction":"down","length":3,"position":{"x":9,"y":25},"solution":"YAW"},{"id":"96-down","group":["96-down"],"separatorLocations":{},"number":96,"humanNumber":"96","clue":" Pride of ex-Sen. Norris","direction":"down","length":3,"position":{"x":0,"y":26},"solution":"TVA"}],"dimensions":{"cols":21,"rows":21},"crosswordType":"genius"}