{"id":"5/21/1995","name":"1995-05-21","date":"0001-01-01T00:00:00","entries":[{"id":"1-across","group":["1-across"],"separatorLocations":{},"number":1,"humanNumber":"1","clue":" Register message","direction":"across","length":6,"position":{"x":0,"y":0},"solution":"NOSALE"},{"id":"7-across","group":["7-across"],"separatorLocations":{},"number":7,"humanNumber":"7","clue":" Slippery _____","direction":"across","length":3,"position":{"x":7,"y":0},"solution":"ELM"},{"id":"10-across","group":["10-across"],"separatorLocations":{},"number":10,"humanNumber":"10","clue":" Clayey deposit","direction":"across","length":4,"position":{"x":11,"y":0},"solution":"MARL"},{"id":"14-across","group":["14-across"],"separatorLocations":{},"number":14,"humanNumber":"14","clue":" Florentine statue","direction":"across","length":5,"position":{"x":1,"y":1},"solution":"DAVID"},{"id":"19-across","group":["19-across"],"separatorLocations":{},"number":19,"humanNumber":"19","clue":" Guyana's _____ Indians","direction":"across","length":6,"position":{"x":6,"y":1},"solution":"ARAWAK"},{"id":"20-across","group":["20-across"],"separatorLocations":{},"number":20,"humanNumber":"20","clue":" Kind of flour","direction":"across","length":3,"position":{"x":13,"y":1},"solution":"SOY"},{"id":"21-across","group":["21-across"],"separatorLocations":{},"number":21,"humanNumber":"21","clue":" Jai _____","direction":"across","length":4,"position":{"x":2,"y":2},"solution":"ALAI"},{"id":"22-across","group":["22-across"],"separatorLocations":{},"number":22,"humanNumber":"22","clue":" \"_____, shine; for thy light is come...\": Isaiah","direction":"across","length":5,"position":{"x":7,"y":2},"solution":"ARISE"},{"id":"23-across","group":["23-across"],"separatorLocations":{},"number":23,"humanNumber":"23","clue":" Vietnamese seaport","direction":"across","length":6,"position":{"x":12,"y":2},"solution":"DANANG"},{"id":"24-across","group":["24-across"],"separatorLocations":{},"number":24,"humanNumber":"24","clue":" ==}:?]]","direction":"across","length":14,"position":{"x":4,"y":3},"solution":"ABRAHAMLINCOLN"},{"id":"27-across","group":["27-across"],"separatorLocations":{},"number":27,"humanNumber":"27","clue":" Bone cavities","direction":"across","length":5,"position":{"x":3,"y":4},"solution":"ANTRA"},{"id":"28-across","group":["28-across"],"separatorLocations":{},"number":28,"humanNumber":"28","clue":" \"Indeed!\" once","direction":"across","length":6,"position":{"x":9,"y":4},"solution":"QUOTHA"},{"id":"29-across","group":["29-across"],"separatorLocations":{},"number":29,"humanNumber":"29","clue":" Former gold coins of Spain","direction":"across","length":8,"position":{"x":1,"y":5},"solution":"PISTOLES"},{"id":"30-across","group":["30-across"],"separatorLocations":{},"number":30,"humanNumber":"30","clue":" Bye-bye","direction":"across","length":5,"position":{"x":11,"y":5},"solution":"ADIEU"},{"id":"32-across","group":["32-across"],"separatorLocations":{},"number":32,"humanNumber":"32","clue":" A good deal","direction":"across","length":4,"position":{"x":3,"y":6},"solution":"LOTS"},{"id":"34-across","group":["34-across"],"separatorLocations":{},"number":34,"humanNumber":"34","clue":" 78-Across's shoe width","direction":"across","length":3,"position":{"x":8,"y":6},"solution":"EEE"},{"id":"35-across","group":["35-across"],"separatorLocations":{},"number":35,"humanNumber":"35","clue":" Short spans","direction":"across","length":4,"position":{"x":0,"y":7},"solution":"SECS"},{"id":"37-across","group":["37-across"],"separatorLocations":{},"number":37,"humanNumber":"37","clue":" 8(:o)","direction":"across","length":11,"position":{"x":5,"y":7},"solution":"MICKEYMOUSE"},{"id":"41-across","group":["41-across"],"separatorLocations":{},"number":41,"humanNumber":"41","clue":" Battle site of 1944","direction":"across","length":4,"position":{"x":2,"y":8},"solution":"STLO"},{"id":"45-across","group":["45-across"],"separatorLocations":{},"number":45,"humanNumber":"45","clue":" Bud","direction":"across","length":3,"position":{"x":6,"y":8},"solution":"PAL"},{"id":"46-across","group":["46-across"],"separatorLocations":{},"number":46,"humanNumber":"46","clue":" It starts \"In the name of Allah...\"","direction":"across","length":5,"position":{"x":10,"y":8},"solution":"KORAN"},{"id":"47-across","group":["47-across"],"separatorLocations":{},"number":47,"humanNumber":"47","clue":" Dada papa","direction":"across","length":3,"position":{"x":2,"y":9},"solution":"ARP"},{"id":"48-across","group":["48-across"],"separatorLocations":{},"number":48,"humanNumber":"48","clue":" Implanted","direction":"across","length":5,"position":{"x":7,"y":9},"solution":"SOWED"},{"id":"49-across","group":["49-across"],"separatorLocations":{},"number":49,"humanNumber":"49","clue":" Basra resident: Var.","direction":"across","length":5,"position":{"x":12,"y":9},"solution":"IRAKI"},{"id":"51-across","group":["51-across"],"separatorLocations":{},"number":51,"humanNumber":"51","clue":" Evidence left behind","direction":"across","length":5,"position":{"x":3,"y":10},"solution":"TRACE"},{"id":"54-across","group":["54-across"],"separatorLocations":{},"number":54,"humanNumber":"54","clue":" Kind of neck","direction":"across","length":3,"position":{"x":9,"y":10},"solution":"EWE"},{"id":"56-across","group":["56-across"],"separatorLocations":{},"number":56,"humanNumber":"56","clue":" Drama kudos","direction":"across","length":5,"position":{"x":13,"y":10},"solution":"OBIES"},{"id":"57-across","group":["57-across"],"separatorLocations":{},"number":57,"humanNumber":"57","clue":" Certain solvents","direction":"across","length":7,"position":{"x":3,"y":11},"solution":"ELUANTS"},{"id":"59-across","group":["59-across"],"separatorLocations":{},"number":59,"humanNumber":"59","clue":" [g-}]","direction":"across","length":12,"position":{"x":11,"y":11},"solution":"COLONELKLINK"},{"id":"62-across","group":["62-across"],"separatorLocations":{},"number":62,"humanNumber":"62","clue":" Mark _____, Oliver of 1968 film","direction":"across","length":6,"position":{"x":9,"y":12},"solution":"LESTER"},{"id":"63-across","group":["63-across"],"separatorLocations":{},"number":63,"humanNumber":"63","clue":" Game full of traps","direction":"across","length":5,"position":{"x":1,"y":13},"solution":"SKEET"},{"id":"64-across","group":["64-across"],"separatorLocations":{},"number":64,"humanNumber":"64","clue":" Newspaper space","direction":"across","length":6,"position":{"x":7,"y":13},"solution":"LINAGE"},{"id":"65-across","group":["65-across"],"separatorLocations":{},"number":65,"humanNumber":"65","clue":" _____ Lee cheesecake","direction":"across","length":4,"position":{"x":4,"y":14},"solution":"SARA"},{"id":"67-across","group":["67-across"],"separatorLocations":{},"number":67,"humanNumber":"67","clue":" Tank","direction":"across","length":3,"position":{"x":9,"y":14},"solution":"VAT"},{"id":"68-across","group":["68-across"],"separatorLocations":{},"number":68,"humanNumber":"68","clue":" Hideaway","direction":"across","length":4,"position":{"x":13,"y":14},"solution":"LAIR"},{"id":"69-across","group":["69-across"],"separatorLocations":{},"number":69,"humanNumber":"69","clue":" Get-together","direction":"across","length":6,"position":{"x":8,"y":15},"solution":"SOCIAL"},{"id":"71-across","group":["71-across"],"separatorLocations":{},"number":71,"humanNumber":"71","clue":" First name in erotica","direction":"across","length":5,"position":{"x":0,"y":16},"solution":"ANAIS"},{"id":"73-across","group":["73-across"],"separatorLocations":{},"number":73,"humanNumber":"73","clue":" Garlicky dish","direction":"across","length":6,"position":{"x":6,"y":16},"solution":"SCAMPI"},{"id":"78-across","group":["78-across"],"separatorLocations":{},"number":78,"humanNumber":"78","clue":" *?(:o)}","direction":"across","length":12,"position":{"x":13,"y":16},"solution":"BOZOTHECLOWN"},{"id":"80-across","group":["80-across"],"separatorLocations":{},"number":80,"humanNumber":"80","clue":" Square-cut-cigar","direction":"across","length":7,"position":{"x":11,"y":17},"solution":"CHEROOT"},{"id":"81-across","group":["81-across"],"separatorLocations":{},"number":81,"humanNumber":"81","clue":" Jazz style","direction":"across","length":5,"position":{"x":3,"y":18},"solution":"BEBOP"},{"id":"82-across","group":["82-across"],"separatorLocations":{},"number":82,"humanNumber":"82","clue":" Sign of a smash","direction":"across","length":3,"position":{"x":9,"y":18},"solution":"SRO"},{"id":"83-across","group":["83-across"],"separatorLocations":{},"number":83,"humanNumber":"83","clue":" Singer Bob Marley, e.g.","direction":"across","length":5,"position":{"x":13,"y":18},"solution":"RASTA"},{"id":"85-across","group":["85-across"],"separatorLocations":{},"number":85,"humanNumber":"85","clue":" Cotton thread","direction":"across","length":5,"position":{"x":4,"y":19},"solution":"LISLE"},{"id":"86-across","group":["86-across"],"separatorLocations":{},"number":86,"humanNumber":"86","clue":" 1919 Edith Day musical","direction":"across","length":5,"position":{"x":9,"y":19},"solution":"IRENE"},{"id":"87-across","group":["87-across"],"separatorLocations":{},"number":87,"humanNumber":"87","clue":" Teacher's grp.","direction":"across","length":3,"position":{"x":1,"y":20},"solution":"NEA"},{"id":"89-across","group":["89-across"],"separatorLocations":{},"number":89,"humanNumber":"89","clue":" One of the archangels","direction":"across","length":5,"position":{"x":6,"y":20},"solution":"URIEL"},{"id":"91-across","group":["91-across"],"separatorLocations":{},"number":91,"humanNumber":"91","clue":" Hog's thigh","direction":"across","length":3,"position":{"x":12,"y":20},"solution":"HAM"},{"id":"92-across","group":["92-across"],"separatorLocations":{},"number":92,"humanNumber":"92","clue":" Brute","direction":"across","length":4,"position":{"x":0,"y":21},"solution":"OGRE"},{"id":"93-across","group":["93-across"],"separatorLocations":{},"number":93,"humanNumber":"93","clue":" I8-#)\"\"'","direction":"across","length":11,"position":{"x":5,"y":21},"solution":"GROUCHOMARX"},{"id":"97-across","group":["97-across"],"separatorLocations":{},"number":97,"humanNumber":"97","clue":" Towel tag","direction":"across","length":4,"position":{"x":2,"y":22},"solution":"HERS"},{"id":"98-across","group":["98-across"],"separatorLocations":{},"number":98,"humanNumber":"98","clue":" Want-ad initials","direction":"across","length":3,"position":{"x":10,"y":22},"solution":"EOE"},{"id":"99-across","group":["99-across"],"separatorLocations":{},"number":99,"humanNumber":"99","clue":" Caboose position","direction":"across","length":4,"position":{"x":14,"y":22},"solution":"REAR"},{"id":"100-across","group":["100-across"],"separatorLocations":{},"number":100,"humanNumber":"100","clue":" Kumiss imbiber","direction":"across","length":5,"position":{"x":5,"y":23},"solution":"NOMAD"},{"id":"102-across","group":["102-across"],"separatorLocations":{},"number":102,"humanNumber":"102","clue":" Convoke","direction":"across","length":8,"position":{"x":12,"y":23},"solution":"ASSEMBLE"},{"id":"107-across","group":["107-across"],"separatorLocations":{},"number":107,"humanNumber":"107","clue":" Spoors","direction":"across","length":6,"position":{"x":6,"y":24},"solution":"TRACKS"},{"id":"110-across","group":["110-across"],"separatorLocations":{},"number":110,"humanNumber":"110","clue":" Author Calvino","direction":"across","length":5,"position":{"x":13,"y":24},"solution":"ITALO"},{"id":"113-across","group":["113-across"],"separatorLocations":{},"number":113,"humanNumber":"113","clue":" CI[:-=)I","direction":"across","length":14,"position":{"x":3,"y":25},"solution":"CHARLIECHAPLIN"},{"id":"115-across","group":["115-across"],"separatorLocations":{},"number":115,"humanNumber":"115","clue":" Speculator","direction":"across","length":6,"position":{"x":3,"y":26},"solution":"PLAYER"},{"id":"116-across","group":["116-across"],"separatorLocations":{},"number":116,"humanNumber":"116","clue":" Begrime, in Britain","direction":"across","length":5,"position":{"x":9,"y":26},"solution":"COLLY"},{"id":"117-across","group":["117-across"],"separatorLocations":{},"number":117,"humanNumber":"117","clue":" When les étoiles come out","direction":"across","length":4,"position":{"x":0,"y":27},"solution":"NUIT"},{"id":"118-across","group":["118-across"],"separatorLocations":{},"number":118,"humanNumber":"118","clue":" Dweller on the Mekong","direction":"across","length":3,"position":{"x":5,"y":27},"solution":"LAO"},{"id":"119-across","group":["119-across"],"separatorLocations":{},"number":119,"humanNumber":"119","clue":" Freshen","direction":"across","length":6,"position":{"x":9,"y":27},"solution":"AERATE"},{"id":"120-across","group":["120-across"],"separatorLocations":{},"number":120,"humanNumber":"120","clue":" Slight","direction":"across","length":5,"position":{"x":0,"y":28},"solution":"TOKEN"},{"id":"121-across","group":["121-across"],"separatorLocations":{},"number":121,"humanNumber":"121","clue":" Preserve, in a way","direction":"across","length":4,"position":{"x":6,"y":28},"solution":"TAPE"},{"id":"122-across","group":["122-across"],"separatorLocations":{},"number":122,"humanNumber":"122","clue":" Cry of pain","direction":"across","length":3,"position":{"x":11,"y":28},"solution":"YOW"},{"id":"123-across","group":["123-across"],"separatorLocations":{},"number":123,"humanNumber":"123","clue":" Criminal evidence","direction":"across","length":6,"position":{"x":0,"y":29},"solution":"PRINTS"},{"id":"1-down","group":["1-down"],"separatorLocations":{},"number":1,"humanNumber":"1","clue":" Nothing, in Nogales","direction":"down","length":4,"position":{"x":0,"y":0},"solution":"NADA"},{"id":"2-down","group":["2-down"],"separatorLocations":{},"number":2,"humanNumber":"2","clue":" Port south of Cartagena","direction":"down","length":4,"position":{"x":1,"y":0},"solution":"ORAN"},{"id":"3-down","group":["3-down"],"separatorLocations":{},"number":3,"humanNumber":"3","clue":" **?:-)}}}}","direction":"down","length":10,"position":{"x":2,"y":0},"solution":"SANTACLAUS"},{"id":"4-down","group":["4-down"],"separatorLocations":{},"number":4,"humanNumber":"4","clue":" Stars and bars, e.g.","direction":"down","length":6,"position":{"x":3,"y":0},"solution":"AWARDS"},{"id":"5-down","group":["5-down"],"separatorLocations":{},"number":5,"humanNumber":"5","clue":" Hawaii island","direction":"down","length":5,"position":{"x":4,"y":0},"solution":"LANAI"},{"id":"6-down","group":["6-down"],"separatorLocations":{},"number":6,"humanNumber":"6","clue":" Record from the heart: Abbr.","direction":"down","length":3,"position":{"x":5,"y":0},"solution":"EKG"},{"id":"7-down","group":["7-down"],"separatorLocations":{},"number":7,"humanNumber":"7","clue":" Jacob's twin","direction":"down","length":4,"position":{"x":7,"y":0},"solution":"ESAU"},{"id":"8-down","group":["8-down"],"separatorLocations":{},"number":8,"humanNumber":"8","clue":" Western livestock peril","direction":"down","length":4,"position":{"x":8,"y":0},"solution":"LOBO"},{"id":"9-down","group":["9-down"],"separatorLocations":{},"number":9,"humanNumber":"9","clue":" Eucalyptus, e.g.","direction":"down","length":6,"position":{"x":9,"y":0},"solution":"MYRTLE"},{"id":"10-down","group":["10-down"],"separatorLocations":{},"number":10,"humanNumber":"10","clue":" Literally \"high-souled\"","direction":"down","length":7,"position":{"x":11,"y":0},"solution":"MAHATMA"},{"id":"11-down","group":["11-down"],"separatorLocations":{},"number":11,"humanNumber":"11","clue":" _____ rigueur (to the fullest extent): Fr.","direction":"down","length":3,"position":{"x":12,"y":0},"solution":"ALA"},{"id":"12-down","group":["12-down"],"separatorLocations":{},"number":12,"humanNumber":"12","clue":" Mover's equipment","direction":"down","length":4,"position":{"x":13,"y":0},"solution":"RAMP"},{"id":"13-down","group":["13-down"],"separatorLocations":{},"number":13,"humanNumber":"13","clue":" Symbols of purity","direction":"down","length":6,"position":{"x":14,"y":0},"solution":"LILIES"},{"id":"14-down","group":["14-down"],"separatorLocations":{},"number":14,"humanNumber":"14","clue":" Pre-Raphaelite Rossetti","direction":"down","length":5,"position":{"x":1,"y":1},"solution":"DANTE"},{"id":"15-down","group":["15-down"],"separatorLocations":{},"number":15,"humanNumber":"15","clue":" Bowed, in music","direction":"down","length":4,"position":{"x":2,"y":1},"solution":"ARCO"},{"id":"16-down","group":["16-down"],"separatorLocations":{},"number":16,"humanNumber":"16","clue":" Early stringed instrument","direction":"down","length":4,"position":{"x":3,"y":1},"solution":"VIOL"},{"id":"17-down","group":["17-down"],"separatorLocations":{},"number":17,"humanNumber":"17","clue":" _____ Royale National Park","direction":"down","length":4,"position":{"x":4,"y":1},"solution":"ISLE"},{"id":"18-down","group":["18-down"],"separatorLocations":{},"number":18,"humanNumber":"18","clue":" Studies","direction":"down","length":4,"position":{"x":5,"y":1},"solution":"DENS"},{"id":"25-down","group":["25-down"],"separatorLocations":{},"number":25,"humanNumber":"25","clue":" Call on a yawl","direction":"down","length":4,"position":{"x":7,"y":3},"solution":"AHOY"},{"id":"26-down","group":["26-down"],"separatorLocations":{},"number":26,"humanNumber":"26","clue":" Encouraging words from a student","direction":"down","length":4,"position":{"x":12,"y":3},"solution":"ISEE"},{"id":"28-down","group":["28-down"],"separatorLocations":{},"number":28,"humanNumber":"28","clue":" Riding whips","direction":"down","length":6,"position":{"x":9,"y":4},"solution":"QUIRTS"},{"id":"31-down","group":["31-down"],"separatorLocations":{},"number":31,"humanNumber":"31","clue":" Comic Philips","direction":"down","length":3,"position":{"x":14,"y":5},"solution":"EMO"},{"id":"33-down","group":["33-down"],"separatorLocations":{},"number":33,"humanNumber":"33","clue":" Theologian Kierkegaard","direction":"down","length":5,"position":{"x":6,"y":6},"solution":"SOREN"},{"id":"35-down","group":["35-down"],"separatorLocations":{},"number":35,"humanNumber":"35","clue":" Fast pitch","direction":"down","length":5,"position":{"x":0,"y":7},"solution":"SPIEL"},{"id":"36-down","group":["36-down"],"separatorLocations":{},"number":36,"humanNumber":"36","clue":" _____ Naval Weapons Station, N.J.","direction":"down","length":5,"position":{"x":1,"y":7},"solution":"EARLE"},{"id":"38-down","group":["38-down"],"separatorLocations":{},"number":38,"humanNumber":"38","clue":" Passenger balloon part","direction":"down","length":3,"position":{"x":7,"y":7},"solution":"CAR"},{"id":"39-down","group":["39-down"],"separatorLocations":{},"number":39,"humanNumber":"39","clue":" Hang of it","direction":"down","length":5,"position":{"x":8,"y":7},"solution":"KNACK"},{"id":"40-down","group":["40-down"],"separatorLocations":{},"number":40,"humanNumber":"40","clue":" Rises, as water","direction":"down","length":7,"position":{"x":13,"y":7},"solution":"UPWELLS"},{"id":"41-down","group":["41-down"],"separatorLocations":{},"number":41,"humanNumber":"41","clue":" Ferber book","direction":"down","length":5,"position":{"x":2,"y":8},"solution":"SOBIG"},{"id":"42-down","group":["42-down"],"separatorLocations":{},"number":42,"humanNumber":"42","clue":" Wind around","direction":"down","length":5,"position":{"x":3,"y":8},"solution":"TWINE"},{"id":"43-down","group":["43-down"],"separatorLocations":{},"number":43,"humanNumber":"43","clue":" Kind of soup","direction":"down","length":4,"position":{"x":4,"y":8},"solution":"LEEK"},{"id":"44-down","group":["44-down"],"separatorLocations":{},"number":44,"humanNumber":"44","clue":" Indulges to the extreme, informally","direction":"down","length":3,"position":{"x":5,"y":8},"solution":"ODS"},{"id":"46-down","group":["46-down"],"separatorLocations":{},"number":46,"humanNumber":"46","clue":" Early TV medium","direction":"down","length":9,"position":{"x":10,"y":8},"solution":"KINESCOPE"},{"id":"48-down","group":["48-down"],"separatorLocations":{},"number":48,"humanNumber":"48","clue":" Battery type","direction":"down","length":9,"position":{"x":7,"y":9},"solution":"SOLARCELL"},{"id":"50-down","group":["50-down"],"separatorLocations":{},"number":50,"humanNumber":"50","clue":" Kit _____ (candy bar brand)","direction":"down","length":3,"position":{"x":0,"y":10},"solution":"KAT"},{"id":"52-down","group":["52-down"],"separatorLocations":{},"number":52,"humanNumber":"52","clue":" Contemporary","direction":"down","length":6,"position":{"x":6,"y":10},"solution":"COEVAL"},{"id":"53-down","group":["53-down"],"separatorLocations":{},"number":53,"humanNumber":"53","clue":" Wife of Henry II","direction":"down","length":7,"position":{"x":7,"y":10},"solution":"ELEANOR"},{"id":"55-down","group":["55-down"],"separatorLocations":{},"number":55,"humanNumber":"55","clue":" Literary pseudonym","direction":"down","length":4,"position":{"x":11,"y":10},"solution":"ELIA"},{"id":"58-down","group":["58-down"],"separatorLocations":{},"number":58,"humanNumber":"58","clue":" Feature","direction":"down","length":5,"position":{"x":8,"y":11},"solution":"TRAIT"},{"id":"60-down","group":["60-down"],"separatorLocations":{},"number":60,"humanNumber":"60","clue":" Ontario-Quebec border river","direction":"down","length":6,"position":{"x":14,"y":11},"solution":"OTTAWA"},{"id":"61-down","group":["61-down"],"separatorLocations":{},"number":61,"humanNumber":"61","clue":" High-calorie snack","direction":"down","length":5,"position":{"x":3,"y":12},"solution":"KNISH"},{"id":"63-down","group":["63-down"],"separatorLocations":{},"number":63,"humanNumber":"63","clue":" Port in 1943 fighting","direction":"down","length":7,"position":{"x":1,"y":13},"solution":"SALERNO"},{"id":"66-down","group":["66-down"],"separatorLocations":{},"number":66,"humanNumber":"66","clue":" Crowd sounds","direction":"down","length":4,"position":{"x":6,"y":14},"solution":"RAHS"},{"id":"69-down","group":["69-down"],"separatorLocations":{},"number":69,"humanNumber":"69","clue":" Dried out","direction":"down","length":5,"position":{"x":8,"y":15},"solution":"SOBER"},{"id":"70-down","group":["70-down"],"separatorLocations":{},"number":70,"humanNumber":"70","clue":" _____ hole (modern worry)","direction":"down","length":5,"position":{"x":9,"y":15},"solution":"OZONE"},{"id":"72-down","group":["72-down"],"separatorLocations":{},"number":72,"humanNumber":"72","clue":" \"To wrap up...\"","direction":"down","length":5,"position":{"x":3,"y":16},"solution":"INSUM"},{"id":"74-down","group":["74-down"],"separatorLocations":{},"number":74,"humanNumber":"74","clue":" Christina's father","direction":"down","length":3,"position":{"x":8,"y":16},"solution":"ARI"},{"id":"75-down","group":["75-down"],"separatorLocations":{},"number":75,"humanNumber":"75","clue":" (¶-)","direction":"down","length":10,"position":{"x":9,"y":16},"solution":"MOSHEDAYAN"},{"id":"76-down","group":["76-down"],"separatorLocations":{},"number":76,"humanNumber":"76","clue":" Kind of extremes","direction":"down","length":5,"position":{"x":10,"y":16},"solution":"POLAR"},{"id":"77-down","group":["77-down"],"separatorLocations":{},"number":77,"humanNumber":"77","clue":" Tabloid twosomes","direction":"down","length":5,"position":{"x":11,"y":16},"solution":"ITEMS"},{"id":"78-down","group":["78-down"],"separatorLocations":{},"number":78,"humanNumber":"78","clue":" North Atlantic sighting","direction":"down","length":4,"position":{"x":13,"y":16},"solution":"BERG"},{"id":"79-down","group":["79-down"],"separatorLocations":{},"number":79,"humanNumber":"79","clue":" _____ de Lion","direction":"down","length":5,"position":{"x":5,"y":17},"solution":"COEUR"},{"id":"80-down","group":["80-down"],"separatorLocations":{},"number":80,"humanNumber":"80","clue":" Stone memorials","direction":"down","length":6,"position":{"x":11,"y":17},"solution":"CAIRNS"},{"id":"81-down","group":["81-down"],"separatorLocations":{},"number":81,"humanNumber":"81","clue":" Such is a life","direction":"down","length":3,"position":{"x":3,"y":18},"solution":"BIO"},{"id":"84-down","group":["84-down"],"separatorLocations":{},"number":84,"humanNumber":"84","clue":" Chorus sound","direction":"down","length":3,"position":{"x":1,"y":19},"solution":"TRA"},{"id":"88-down","group":["88-down"],"separatorLocations":{},"number":88,"humanNumber":"88","clue":" Old recording disk","direction":"down","length":7,"position":{"x":3,"y":20},"solution":"ACETATE"},{"id":"90-down","group":["90-down"],"separatorLocations":{},"number":90,"humanNumber":"90","clue":" Prefix meaning \"outer\"","direction":"down","length":3,"position":{"x":9,"y":20},"solution":"EXO"},{"id":"93-down","group":["93-down"],"separatorLocations":{},"number":93,"humanNumber":"93","clue":" Vast desert","direction":"down","length":4,"position":{"x":5,"y":21},"solution":"GOBI"},{"id":"94-down","group":["94-down"],"separatorLocations":{},"number":94,"humanNumber":"94","clue":" Give some slack","direction":"down","length":6,"position":{"x":6,"y":21},"solution":"RELENT"},{"id":"95-down","group":["95-down"],"separatorLocations":{},"number":95,"humanNumber":"95","clue":" Beethoven's \"_____ Quartet\"","direction":"down","length":4,"position":{"x":10,"y":21},"solution":"HARP"},{"id":"96-down","group":["96-down"],"separatorLocations":{},"number":96,"humanNumber":"96","clue":" One way to convey information","direction":"down","length":6,"position":{"x":11,"y":21},"solution":"ORALLY"},{"id":"97-down","group":["97-down"],"separatorLocations":{},"number":97,"humanNumber":"97","clue":" John Wayne film","direction":"down","length":6,"position":{"x":2,"y":22},"solution":"HATARI"},{"id":"98-down","group":["98-down"],"separatorLocations":{},"number":98,"humanNumber":"98","clue":" Welsh actor Williams","direction":"down","length":5,"position":{"x":10,"y":22},"solution":"EMLYN"},{"id":"101-down","group":["101-down"],"separatorLocations":{},"number":101,"humanNumber":"101","clue":" One making rapid strides","direction":"down","length":5,"position":{"x":7,"y":23},"solution":"MILER"},{"id":"102-down","group":["102-down"],"separatorLocations":{},"number":102,"humanNumber":"102","clue":" S&L deposit","direction":"down","length":4,"position":{"x":12,"y":23},"solution":"ACCT"},{"id":"103-down","group":["103-down"],"separatorLocations":{},"number":103,"humanNumber":"103","clue":" \"Out!\"","direction":"down","length":4,"position":{"x":13,"y":23},"solution":"SHOO"},{"id":"104-down","group":["104-down"],"separatorLocations":{},"number":104,"humanNumber":"104","clue":" _____ vaccine","direction":"down","length":4,"position":{"x":14,"y":23},"solution":"SALK"},{"id":"105-down","group":["105-down"],"separatorLocations":{},"number":105,"humanNumber":"105","clue":" First name in mysteries","direction":"down","length":4,"position":{"x":0,"y":24},"solution":"ERLE"},{"id":"106-down","group":["106-down"],"separatorLocations":{},"number":106,"humanNumber":"106","clue":" S.A. country","direction":"down","length":4,"position":{"x":4,"y":24},"solution":"ECUA"},{"id":"108-down","group":["108-down"],"separatorLocations":{},"number":108,"humanNumber":"108","clue":" Bye-bye","direction":"down","length":4,"position":{"x":9,"y":24},"solution":"CIAO"},{"id":"109-down","group":["109-down"],"separatorLocations":{},"number":109,"humanNumber":"109","clue":" Be close to","direction":"down","length":4,"position":{"x":10,"y":24},"solution":"KNOW"},{"id":"111-down","group":["111-down"],"separatorLocations":{},"number":111,"humanNumber":"111","clue":" Riga denizen","direction":"down","length":4,"position":{"x":1,"y":25},"solution":"LETT"},{"id":"112-down","group":["112-down"],"separatorLocations":{},"number":112,"humanNumber":"112","clue":" Assayers assay them","direction":"down","length":4,"position":{"x":2,"y":25},"solution":"ORES"},{"id":"114-down","group":["114-down"],"separatorLocations":{},"number":114,"humanNumber":"114","clue":" With it","direction":"down","length":3,"position":{"x":11,"y":25},"solution":"HIP"},{"id":"115-down","group":["115-down"],"separatorLocations":{},"number":115,"humanNumber":"115","clue":" Twaddle","direction":"down","length":3,"position":{"x":3,"y":26},"solution":"PAP"}],"dimensions":{"cols":21,"rows":21},"crosswordType":"genius"}