{"id":"6/22/2002","name":"2002-06-22","date":"0001-01-01T00:00:00","entries":[{"id":"1-across","group":["1-across"],"separatorLocations":{},"number":1,"humanNumber":"1","clue":" Leave behind","direction":"across","length":8,"position":{"x":0,"y":0},"solution":"SHAKEOFF"},{"id":"9-across","group":["9-across"],"separatorLocations":{},"number":9,"humanNumber":"9","clue":" Beliefs","direction":"across","length":6,"position":{"x":9,"y":0},"solution":"DOGMAS"},{"id":"15-across","group":["15-across"],"separatorLocations":{},"number":15,"humanNumber":"15","clue":" Entertain, as guests","direction":"across","length":8,"position":{"x":0,"y":1},"solution":"HAVEOVER"},{"id":"16-across","group":["16-across"],"separatorLocations":{},"number":16,"humanNumber":"16","clue":" Skater Zayak","direction":"across","length":6,"position":{"x":9,"y":1},"solution":"ELAINE"},{"id":"17-across","group":["17-across"],"separatorLocations":{},"number":17,"humanNumber":"17","clue":" \"___ was in our lips and eyes\": \"Antony and Cleopatra\"","direction":"across","length":8,"position":{"x":0,"y":2},"solution":"ETERNITY"},{"id":"18-across","group":["18-across"],"separatorLocations":{},"number":18,"humanNumber":"18","clue":" Rebate card, e.g.","direction":"across","length":6,"position":{"x":9,"y":2},"solution":"MAILIN"},{"id":"19-across","group":["19-across"],"separatorLocations":{},"number":19,"humanNumber":"19","clue":" Hay there","direction":"across","length":4,"position":{"x":0,"y":3},"solution":"BARN"},{"id":"20-across","group":["20-across"],"separatorLocations":{},"number":20,"humanNumber":"20","clue":" Vital moment","direction":"across","length":10,"position":{"x":5,"y":3},"solution":"NICKOFTIME"},{"id":"22-across","group":["22-across"],"separatorLocations":{},"number":22,"humanNumber":"22","clue":" Hosp. areas","direction":"across","length":3,"position":{"x":0,"y":4},"solution":"ORS"},{"id":"23-across","group":["23-across"],"separatorLocations":{},"number":23,"humanNumber":"23","clue":" Particle in a quark model","direction":"across","length":5,"position":{"x":4,"y":4},"solution":"MESON"},{"id":"24-across","group":["24-across"],"separatorLocations":{},"number":24,"humanNumber":"24","clue":" Solo","direction":"across","length":4,"position":{"x":11,"y":4},"solution":"STAG"},{"id":"25-across","group":["25-across"],"separatorLocations":{},"number":25,"humanNumber":"25","clue":" Devotion","direction":"across","length":5,"position":{"x":0,"y":5},"solution":"PIETY"},{"id":"27-across","group":["27-across"],"separatorLocations":{},"number":27,"humanNumber":"27","clue":" Some farm hands","direction":"across","length":5,"position":{"x":6,"y":5},"solution":"HOERS"},{"id":"30-across","group":["30-across"],"separatorLocations":{},"number":30,"humanNumber":"30","clue":" ___ premium","direction":"across","length":3,"position":{"x":12,"y":5},"solution":"ATA"},{"id":"31-across","group":["31-across"],"separatorLocations":{},"number":31,"humanNumber":"31","clue":" Punch lines?","direction":"across","length":3,"position":{"x":3,"y":6},"solution":"OWS"},{"id":"33-across","group":["33-across"],"separatorLocations":{},"number":33,"humanNumber":"33","clue":" 1920's Japanese premier","direction":"across","length":4,"position":{"x":7,"y":6},"solution":"KATO"},{"id":"34-across","group":["34-across"],"separatorLocations":{},"number":34,"humanNumber":"34","clue":" It's faith-based: Abbr.","direction":"across","length":3,"position":{"x":12,"y":6},"solution":"REL"},{"id":"35-across","group":["35-across"],"separatorLocations":{},"number":35,"humanNumber":"35","clue":" Drop down","direction":"across","length":6,"position":{"x":1,"y":7},"solution":"DEMOTE"},{"id":"38-across","group":["38-across"],"separatorLocations":{},"number":38,"humanNumber":"38","clue":" Airport woes","direction":"across","length":6,"position":{"x":8,"y":7},"solution":"DELAYS"},{"id":"40-across","group":["40-across"],"separatorLocations":{},"number":40,"humanNumber":"40","clue":" ___ scripta (statute)","direction":"across","length":3,"position":{"x":0,"y":8},"solution":"LEX"},{"id":"41-across","group":["41-across"],"separatorLocations":{},"number":41,"humanNumber":"41","clue":" Reddish","direction":"across","length":4,"position":{"x":4,"y":8},"solution":"RARE"},{"id":"43-across","group":["43-across"],"separatorLocations":{},"number":43,"humanNumber":"43","clue":" Cuisinier's need","direction":"across","length":3,"position":{"x":9,"y":8},"solution":"SEL"},{"id":"44-across","group":["44-across"],"separatorLocations":{},"number":44,"humanNumber":"44","clue":" \"Oh!\" overseas","direction":"across","length":3,"position":{"x":0,"y":9},"solution":"ACH"},{"id":"45-across","group":["45-across"],"separatorLocations":{},"number":45,"humanNumber":"45","clue":" Not getting many laughs, as a comedian","direction":"across","length":5,"position":{"x":4,"y":9},"solution":"DYING"},{"id":"47-across","group":["47-across"],"separatorLocations":{},"number":47,"humanNumber":"47","clue":" Central position","direction":"across","length":5,"position":{"x":10,"y":9},"solution":"MIDST"},{"id":"51-across","group":["51-across"],"separatorLocations":{},"number":51,"humanNumber":"51","clue":" Mess-up","direction":"across","length":4,"position":{"x":0,"y":10},"solution":"SLIP"},{"id":"53-across","group":["53-across"],"separatorLocations":{},"number":53,"humanNumber":"53","clue":" Conk","direction":"across","length":5,"position":{"x":6,"y":10},"solution":"CROWN"},{"id":"55-across","group":["55-across"],"separatorLocations":{},"number":55,"humanNumber":"55","clue":" Taxonomic suffix","direction":"across","length":3,"position":{"x":12,"y":10},"solution":"OTA"},{"id":"56-across","group":["56-across"],"separatorLocations":{},"number":56,"humanNumber":"56","clue":" Predetermined fare","direction":"across","length":10,"position":{"x":0,"y":11},"solution":"TABLEDHOTE"},{"id":"59-across","group":["59-across"],"separatorLocations":{},"number":59,"humanNumber":"59","clue":" Warning device","direction":"across","length":4,"position":{"x":11,"y":11},"solution":"HORN"},{"id":"60-across","group":["60-across"],"separatorLocations":{},"number":60,"humanNumber":"60","clue":" Jim Palmer, notably","direction":"across","length":6,"position":{"x":0,"y":12},"solution":"ORIOLE"},{"id":"61-across","group":["61-across"],"separatorLocations":{},"number":61,"humanNumber":"61","clue":" Like a grenade reaching a bunker, maybe","direction":"across","length":8,"position":{"x":7,"y":12},"solution":"LOBBEDIN"},{"id":"63-across","group":["63-across"],"separatorLocations":{},"number":63,"humanNumber":"63","clue":" Bug","direction":"across","length":6,"position":{"x":0,"y":13},"solution":"NETTLE"},{"id":"64-across","group":["64-across"],"separatorLocations":{},"number":64,"humanNumber":"64","clue":" Have insomnia","direction":"across","length":8,"position":{"x":7,"y":13},"solution":"LIEAWAKE"},{"id":"65-across","group":["65-across"],"separatorLocations":{},"number":65,"humanNumber":"65","clue":" Point's opposite?","direction":"across","length":6,"position":{"x":0,"y":14},"solution":"ERASER"},{"id":"66-across","group":["66-across"],"separatorLocations":{},"number":66,"humanNumber":"66","clue":" High and dry","direction":"across","length":8,"position":{"x":7,"y":14},"solution":"STRANDED"},{"id":"1-down","group":["1-down"],"separatorLocations":{},"number":1,"humanNumber":"1","clue":" 1984 Cyndi Lauper hit","direction":"down","length":6,"position":{"x":0,"y":0},"solution":"SHEBOP"},{"id":"2-down","group":["2-down"],"separatorLocations":{},"number":2,"humanNumber":"2","clue":" John Wayne adventure film","direction":"down","length":6,"position":{"x":1,"y":0},"solution":"HATARI"},{"id":"3-down","group":["3-down"],"separatorLocations":{},"number":3,"humanNumber":"3","clue":" Objecting","direction":"down","length":6,"position":{"x":2,"y":0},"solution":"AVERSE"},{"id":"4-down","group":["4-down"],"separatorLocations":{},"number":4,"humanNumber":"4","clue":" Composer of Broadway's \"Sunny\"","direction":"down","length":4,"position":{"x":3,"y":0},"solution":"KERN"},{"id":"5-down","group":["5-down"],"separatorLocations":{},"number":5,"humanNumber":"5","clue":" Ages","direction":"down","length":3,"position":{"x":4,"y":0},"solution":"EON"},{"id":"6-down","group":["6-down"],"separatorLocations":{},"number":6,"humanNumber":"6","clue":" Like bighorns","direction":"down","length":5,"position":{"x":5,"y":0},"solution":"OVINE"},{"id":"7-down","group":["7-down"],"separatorLocations":{},"number":7,"humanNumber":"7","clue":" Charm","direction":"down","length":6,"position":{"x":6,"y":0},"solution":"FETISH"},{"id":"8-down","group":["8-down"],"separatorLocations":{},"number":8,"humanNumber":"8","clue":" Diner employee","direction":"down","length":7,"position":{"x":7,"y":0},"solution":"FRYCOOK"},{"id":"9-down","group":["9-down"],"separatorLocations":{},"number":9,"humanNumber":"9","clue":" Certain tape","direction":"down","length":4,"position":{"x":9,"y":0},"solution":"DEMO"},{"id":"10-down","group":["10-down"],"separatorLocations":{},"number":10,"humanNumber":"10","clue":" Minnesota's St. ___ College","direction":"down","length":4,"position":{"x":10,"y":0},"solution":"OLAF"},{"id":"11-down","group":["11-down"],"separatorLocations":{},"number":11,"humanNumber":"11","clue":" Ambles and others","direction":"down","length":5,"position":{"x":11,"y":0},"solution":"GAITS"},{"id":"12-down","group":["12-down"],"separatorLocations":{},"number":12,"humanNumber":"12","clue":" Common career choice, with \"the\"","direction":"down","length":8,"position":{"x":12,"y":0},"solution":"MILITARY"},{"id":"13-down","group":["13-down"],"separatorLocations":{},"number":13,"humanNumber":"13","clue":" Gets going","direction":"down","length":8,"position":{"x":13,"y":0},"solution":"ANIMATES"},{"id":"14-down","group":["14-down"],"separatorLocations":{},"number":14,"humanNumber":"14","clue":" Gambia's only neighbor","direction":"down","length":7,"position":{"x":14,"y":0},"solution":"SENEGAL"},{"id":"21-down","group":["21-down"],"separatorLocations":{},"number":21,"humanNumber":"21","clue":" Press, fold and stretch","direction":"down","length":5,"position":{"x":8,"y":3},"solution":"KNEAD"},{"id":"23-down","group":["23-down"],"separatorLocations":{},"number":23,"humanNumber":"23","clue":" Astonished cry","direction":"down","length":6,"position":{"x":4,"y":4},"solution":"MYWORD"},{"id":"26-down","group":["26-down"],"separatorLocations":{},"number":26,"humanNumber":"26","clue":" Alley denizen","direction":"down","length":3,"position":{"x":3,"y":5},"solution":"TOM"},{"id":"28-down","group":["28-down"],"separatorLocations":{},"number":28,"humanNumber":"28","clue":" Many begin with I: Abbr.","direction":"down","length":4,"position":{"x":9,"y":5},"solution":"RTES"},{"id":"29-down","group":["29-down"],"separatorLocations":{},"number":29,"humanNumber":"29","clue":" Kind of oath","direction":"down","length":6,"position":{"x":10,"y":5},"solution":"SOLEMN"},{"id":"32-down","group":["32-down"],"separatorLocations":{},"number":32,"humanNumber":"32","clue":" Host's request","direction":"down","length":4,"position":{"x":5,"y":6},"solution":"STAY"},{"id":"35-down","group":["35-down"],"separatorLocations":{},"number":35,"humanNumber":"35","clue":" Dummy's opposite","direction":"down","length":8,"position":{"x":1,"y":7},"solution":"DECLARER"},{"id":"36-down","group":["36-down"],"separatorLocations":{},"number":36,"humanNumber":"36","clue":" Start of a court presentation","direction":"down","length":8,"position":{"x":2,"y":7},"solution":"EXHIBITA"},{"id":"37-down","group":["37-down"],"separatorLocations":{},"number":37,"humanNumber":"37","clue":" Expressionist painter Heckel","direction":"down","length":5,"position":{"x":6,"y":7},"solution":"ERICH"},{"id":"39-down","group":["39-down"],"separatorLocations":{},"number":39,"humanNumber":"39","clue":" His won-lost record was 56-5","direction":"down","length":3,"position":{"x":11,"y":7},"solution":"ALI"},{"id":"40-down","group":["40-down"],"separatorLocations":{},"number":40,"humanNumber":"40","clue":" Hawker's tempting words","direction":"down","length":7,"position":{"x":0,"y":8},"solution":"LASTONE"},{"id":"42-down","group":["42-down"],"separatorLocations":{},"number":42,"humanNumber":"42","clue":" Records","direction":"down","length":7,"position":{"x":7,"y":8},"solution":"ENROLLS"},{"id":"46-down","group":["46-down"],"separatorLocations":{},"number":46,"humanNumber":"46","clue":" Begin immediately","direction":"down","length":6,"position":{"x":8,"y":9},"solution":"GOTOIT"},{"id":"48-down","group":["48-down"],"separatorLocations":{},"number":48,"humanNumber":"48","clue":" Thingy","direction":"down","length":6,"position":{"x":12,"y":9},"solution":"DOODAD"},{"id":"49-down","group":["49-down"],"separatorLocations":{},"number":49,"humanNumber":"49","clue":" Call at home","direction":"down","length":6,"position":{"x":13,"y":9},"solution":"STRIKE"},{"id":"50-down","group":["50-down"],"separatorLocations":{},"number":50,"humanNumber":"50","clue":" Thrashed","direction":"down","length":6,"position":{"x":14,"y":9},"solution":"TANNED"},{"id":"52-down","group":["52-down"],"separatorLocations":{},"number":52,"humanNumber":"52","clue":" They may be brewing","direction":"down","length":5,"position":{"x":3,"y":10},"solution":"PLOTS"},{"id":"54-down","group":["54-down"],"separatorLocations":{},"number":54,"humanNumber":"54","clue":" \"Cubist Poems\" writer Max","direction":"down","length":5,"position":{"x":9,"y":10},"solution":"WEBER"},{"id":"57-down","group":["57-down"],"separatorLocations":{},"number":57,"humanNumber":"57","clue":" Women's issue?","direction":"down","length":4,"position":{"x":4,"y":11},"solution":"ELLE"},{"id":"58-down","group":["58-down"],"separatorLocations":{},"number":58,"humanNumber":"58","clue":" Bucks","direction":"down","length":4,"position":{"x":5,"y":11},"solution":"DEER"},{"id":"59-down","group":["59-down"],"separatorLocations":{},"number":59,"humanNumber":"59","clue":" Cut","direction":"down","length":4,"position":{"x":11,"y":11},"solution":"HEWN"},{"id":"62-down","group":["62-down"],"separatorLocations":{},"number":62,"humanNumber":"62","clue":" Bucolic cry","direction":"down","length":3,"position":{"x":10,"y":12},"solution":"BAA"}],"dimensions":{"cols":15,"rows":15},"crosswordType":"genius"}