{"id":"4/3/2011","name":"2011-04-03","date":"0001-01-01T00:00:00","entries":[{"id":"1-across","group":["1-across"],"separatorLocations":{},"number":1,"humanNumber":"1","clue":" Henry II player in \"Becket\"","direction":"across","length":6,"position":{"x":0,"y":0},"solution":"OTOOLE"},{"id":"7-across","group":["7-across"],"separatorLocations":{},"number":7,"humanNumber":"7","clue":" Something that might get a rise out of people?","direction":"across","length":6,"position":{"x":7,"y":0},"solution":"ANTHEM"},{"id":"13-across","group":["13-across"],"separatorLocations":{},"number":13,"humanNumber":"13","clue":" Clinch","direction":"across","length":3,"position":{"x":14,"y":0},"solution":"ICE"},{"id":"16-across","group":["16-across"],"separatorLocations":{},"number":16,"humanNumber":"16","clue":" Clinch, with \"up\"","direction":"across","length":3,"position":{"x":3,"y":1},"solution":"SEW"},{"id":"19-across","group":["19-across"],"separatorLocations":{},"number":19,"humanNumber":"19","clue":" Arrange again","direction":"across","length":6,"position":{"x":6,"y":1},"solution":"REPLAN"},{"id":"20-across","group":["20-across"],"separatorLocations":{},"number":20,"humanNumber":"20","clue":" Suburb of San Diego","direction":"across","length":6,"position":{"x":13,"y":1},"solution":"LAMESA"},{"id":"21-across","group":["21-across"],"separatorLocations":{},"number":21,"humanNumber":"21","clue":" \"Livin' on a Prayer\" band","direction":"across","length":7,"position":{"x":5,"y":2},"solution":"BONJOVI"},{"id":"23-across","group":["23-across"],"separatorLocations":{},"number":23,"humanNumber":"23","clue":" Chinese restaurant offering / Wonderland affair / Group on the left?","direction":"across","length":13,"position":{"x":12,"y":2},"solution":"GREENTEAPARTY"},{"id":"25-across","group":["25-across"],"separatorLocations":{},"number":25,"humanNumber":"25","clue":" Indigenous","direction":"across","length":7,"position":{"x":11,"y":3},"solution":"ENDEMIC"},{"id":"26-across","group":["26-across"],"separatorLocations":{},"number":26,"humanNumber":"26","clue":" Neo, for one","direction":"across","length":7,"position":{"x":4,"y":4},"solution":"ANAGRAM"},{"id":"27-across","group":["27-across"],"separatorLocations":{},"number":27,"humanNumber":"27","clue":" Baltimore specialty / Effortless task / Move on all fours with the belly up","direction":"across","length":12,"position":{"x":12,"y":4},"solution":"CRABCAKEWALK"},{"id":"29-across","group":["29-across"],"separatorLocations":{},"number":29,"humanNumber":"29","clue":" Admit","direction":"across","length":5,"position":{"x":13,"y":5},"solution":"LETON"},{"id":"31-across","group":["31-across"],"separatorLocations":{},"number":31,"humanNumber":"31","clue":" Skins, e.g.","direction":"across","length":4,"position":{"x":5,"y":6},"solution":"TEAM"},{"id":"32-across","group":["32-across"],"separatorLocations":{},"number":32,"humanNumber":"32","clue":" Ancient city NW of Carthage","direction":"across","length":5,"position":{"x":0,"y":7},"solution":"UTICA"},{"id":"36-across","group":["36-across"],"separatorLocations":{},"number":36,"humanNumber":"36","clue":" Most red, maybe","direction":"across","length":6,"position":{"x":8,"y":7},"solution":"RIPEST"},{"id":"39-across","group":["39-across"],"separatorLocations":{},"number":39,"humanNumber":"39","clue":" Firmly fixed","direction":"across","length":4,"position":{"x":0,"y":8},"solution":"FAST"},{"id":"43-across","group":["43-across"],"separatorLocations":{},"number":43,"humanNumber":"43","clue":" Plunging / Play hooky / Vulgar","direction":"across","length":11,"position":{"x":6,"y":8},"solution":"LOWCUTCLASS"},{"id":"47-across","group":["47-across"],"separatorLocations":{},"number":47,"humanNumber":"47","clue":" Scrunchies","direction":"across","length":8,"position":{"x":4,"y":9},"solution":"HAIRTIES"},{"id":"51-across","group":["51-across"],"separatorLocations":{},"number":51,"humanNumber":"51","clue":" Tip reducer?","direction":"across","length":8,"position":{"x":12,"y":9},"solution":"NAILFILE"},{"id":"52-across","group":["52-across"],"separatorLocations":{},"number":52,"humanNumber":"52","clue":" Northern flier / Mixer maker / Put on the line","direction":"across","length":12,"position":{"x":6,"y":10},"solution":"AIRCANADADRY"},{"id":"55-across","group":["55-across"],"separatorLocations":{},"number":55,"humanNumber":"55","clue":" Buffoon","direction":"across","length":3,"position":{"x":3,"y":11},"solution":"ASS"},{"id":"56-across","group":["56-across"],"separatorLocations":{},"number":56,"humanNumber":"56","clue":" Lure","direction":"across","length":5,"position":{"x":8,"y":11},"solution":"SIREN"},{"id":"58-across","group":["58-across"],"separatorLocations":{},"number":58,"humanNumber":"58","clue":" Idiots","direction":"across","length":5,"position":{"x":14,"y":11},"solution":"YOYOS"},{"id":"59-across","group":["59-across"],"separatorLocations":{},"number":59,"humanNumber":"59","clue":" \"Up to ___,\" 1952 game show","direction":"across","length":4,"position":{"x":5,"y":12},"solution":"PAAR"},{"id":"60-across","group":["60-across"],"separatorLocations":{},"number":60,"humanNumber":"60","clue":" ___ Hunt, Tom Cruise's character in \"Mission: Impossible\"","direction":"across","length":5,"position":{"x":9,"y":12},"solution":"ETHAN"},{"id":"63-across","group":["63-across"],"separatorLocations":{},"number":63,"humanNumber":"63","clue":" Sénat vote","direction":"across","length":3,"position":{"x":0,"y":13},"solution":"NON"},{"id":"64-across","group":["64-across"],"separatorLocations":{},"number":64,"humanNumber":"64","clue":" God of shepherds","direction":"across","length":3,"position":{"x":4,"y":13},"solution":"PAN"},{"id":"65-across","group":["65-across"],"separatorLocations":{},"number":65,"humanNumber":"65","clue":" Dials","direction":"across","length":5,"position":{"x":9,"y":13},"solution":"CALLS"},{"id":"67-across","group":["67-across"],"separatorLocations":{},"number":67,"humanNumber":"67","clue":" Yellowish brown / Bit of \"dumb\" humor / Many a forwarded e-mail","direction":"across","length":15,"position":{"x":3,"y":14},"solution":"DIRTYBLONDEJOKE"},{"id":"72-across","group":["72-across"],"separatorLocations":{},"number":72,"humanNumber":"72","clue":" Hot cider server","direction":"across","length":5,"position":{"x":7,"y":15},"solution":"LADLE"},{"id":"74-across","group":["74-across"],"separatorLocations":{},"number":74,"humanNumber":"74","clue":" Seat for toddlers","direction":"across","length":3,"position":{"x":14,"y":15},"solution":"LAP"},{"id":"75-across","group":["75-across"],"separatorLocations":{},"number":75,"humanNumber":"75","clue":" Time, in Torino","direction":"across","length":3,"position":{"x":3,"y":16},"solution":"ORA"},{"id":"76-across","group":["76-across"],"separatorLocations":{},"number":76,"humanNumber":"76","clue":" Indo-___","direction":"across","length":5,"position":{"x":7,"y":16},"solution":"ARYAN"},{"id":"80-across","group":["80-across"],"separatorLocations":{},"number":80,"humanNumber":"80","clue":" Item for a mason","direction":"across","length":4,"position":{"x":12,"y":16},"solution":"TILE"},{"id":"81-across","group":["81-across"],"separatorLocations":{},"number":81,"humanNumber":"81","clue":" Previous","direction":"across","length":5,"position":{"x":2,"y":17},"solution":"PRIOR"},{"id":"84-across","group":["84-across"],"separatorLocations":{},"number":84,"humanNumber":"84","clue":" Idiotic","direction":"across","length":5,"position":{"x":8,"y":17},"solution":"CRAZY"},{"id":"86-across","group":["86-across"],"separatorLocations":{},"number":86,"humanNumber":"86","clue":" Wonderment","direction":"across","length":3,"position":{"x":0,"y":18},"solution":"AWE"},{"id":"87-across","group":["87-across"],"separatorLocations":{},"number":87,"humanNumber":"87","clue":" Cause of congestion / Detective's challenge / Loony","direction":"across","length":12,"position":{"x":3,"y":18},"solution":"HEADCOLDCASE"},{"id":"90-across","group":["90-across"],"separatorLocations":{},"number":90,"humanNumber":"90","clue":" Style of chicken","direction":"across","length":8,"position":{"x":1,"y":19},"solution":"SZECHWAN"},{"id":"93-across","group":["93-across"],"separatorLocations":{},"number":93,"humanNumber":"93","clue":" \"Naturally!\"","direction":"across","length":8,"position":{"x":9,"y":19},"solution":"OFCOURSE"},{"id":"94-across","group":["94-across"],"separatorLocations":{},"number":94,"humanNumber":"94","clue":" Winnie-the-Pooh possession / Baked entree / Sweetie","direction":"across","length":11,"position":{"x":4,"y":20},"solution":"HONEYPOTPIE"},{"id":"96-across","group":["96-across"],"separatorLocations":{},"number":96,"humanNumber":"96","clue":" Grow together","direction":"across","length":4,"position":{"x":2,"y":21},"solution":"KNIT"},{"id":"97-across","group":["97-across"],"separatorLocations":{},"number":97,"humanNumber":"97","clue":" Best to follow, as advice","direction":"across","length":6,"position":{"x":7,"y":21},"solution":"SAGEST"},{"id":"100-across","group":["100-across"],"separatorLocations":{},"number":100,"humanNumber":"100","clue":" Attention getters","direction":"across","length":5,"position":{"x":1,"y":22},"solution":"PSSTS"},{"id":"101-across","group":["101-across"],"separatorLocations":{},"number":101,"humanNumber":"101","clue":" It's no good when it's flat","direction":"across","length":4,"position":{"x":12,"y":22},"solution":"COLA"},{"id":"102-across","group":["102-across"],"separatorLocations":{},"number":102,"humanNumber":"102","clue":" Hero","direction":"across","length":5,"position":{"x":3,"y":23},"solution":"HOAGY"},{"id":"106-across","group":["106-across"],"separatorLocations":{},"number":106,"humanNumber":"106","clue":" Fancy Feast product / Cafeteria outburst / \"Mean Girls\" event","direction":"across","length":12,"position":{"x":12,"y":23},"solution":"CATFOODFIGHT"},{"id":"114-across","group":["114-across"],"separatorLocations":{},"number":114,"humanNumber":"114","clue":" Hooded jackets","direction":"across","length":7,"position":{"x":10,"y":24},"solution":"ANORAKS"},{"id":"118-across","group":["118-across"],"separatorLocations":{},"number":118,"humanNumber":"118","clue":" ___ sunglasses","direction":"across","length":7,"position":{"x":3,"y":25},"solution":"AVIATOR"},{"id":"119-across","group":["119-across"],"separatorLocations":{},"number":119,"humanNumber":"119","clue":" Democratic territory / Cardinal, e.g. / \"Over the Rainbow\" flier","direction":"across","length":13,"position":{"x":11,"y":25},"solution":"BLUESTATEBIRD"},{"id":"122-across","group":["122-across"],"separatorLocations":{},"number":122,"humanNumber":"122","clue":" Biracial Latin American","direction":"across","length":7,"position":{"x":9,"y":26},"solution":"MESTIZO"},{"id":"123-across","group":["123-across"],"separatorLocations":{},"number":123,"humanNumber":"123","clue":" \"Ditto!\"","direction":"across","length":6,"position":{"x":2,"y":27},"solution":"IAGREE"},{"id":"124-across","group":["124-across"],"separatorLocations":{},"number":124,"humanNumber":"124","clue":" 1966 best seller set in Hong Kong","direction":"across","length":6,"position":{"x":9,"y":27},"solution":"TAIPAN"},{"id":"125-across","group":["125-across"],"separatorLocations":{},"number":125,"humanNumber":"125","clue":" See 126-Across","direction":"across","length":3,"position":{"x":0,"y":28},"solution":"SCH"},{"id":"126-across","group":["126-across"],"separatorLocations":{},"number":126,"humanNumber":"126","clue":" Half a 125-Across year: Abbr.","direction":"across","length":3,"position":{"x":4,"y":28},"solution":"SEM"},{"id":"127-across","group":["127-across"],"separatorLocations":{},"number":127,"humanNumber":"127","clue":" They might be crossed","direction":"across","length":6,"position":{"x":8,"y":28},"solution":"SWORDS"},{"id":"128-across","group":["128-across"],"separatorLocations":{},"number":128,"humanNumber":"128","clue":" \"The Battleship Potemkin\" setting","direction":"across","length":6,"position":{"x":0,"y":29},"solution":"ODESSA"},{"id":"1-down","group":["1-down"],"separatorLocations":{},"number":1,"humanNumber":"1","clue":" Alternative to gov","direction":"down","length":3,"position":{"x":0,"y":0},"solution":"ORG"},{"id":"2-down","group":["2-down"],"separatorLocations":{},"number":2,"humanNumber":"2","clue":" Trillion: Prefix","direction":"down","length":4,"position":{"x":1,"y":0},"solution":"TERA"},{"id":"3-down","group":["3-down"],"separatorLocations":{},"number":3,"humanNumber":"3","clue":" Word with French or U.S.","direction":"down","length":4,"position":{"x":2,"y":0},"solution":"OPEN"},{"id":"4-down","group":["4-down"],"separatorLocations":{},"number":4,"humanNumber":"4","clue":" Olive genus","direction":"down","length":4,"position":{"x":3,"y":0},"solution":"OLEA"},{"id":"5-down","group":["5-down"],"separatorLocations":{},"number":5,"humanNumber":"5","clue":" Cross-country skiing","direction":"down","length":8,"position":{"x":4,"y":0},"solution":"LANGLAUF"},{"id":"6-down","group":["6-down"],"separatorLocations":{},"number":6,"humanNumber":"6","clue":" ___ deux âges (middle-aged: Fr.)","direction":"down","length":5,"position":{"x":5,"y":0},"solution":"ENTRE"},{"id":"7-down","group":["7-down"],"separatorLocations":{},"number":7,"humanNumber":"7","clue":" John Wayne western, with \"The\"","direction":"down","length":5,"position":{"x":7,"y":0},"solution":"ALAMO"},{"id":"8-down","group":["8-down"],"separatorLocations":{},"number":8,"humanNumber":"8","clue":" Toddler's need","direction":"down","length":3,"position":{"x":8,"y":0},"solution":"NAP"},{"id":"9-down","group":["9-down"],"separatorLocations":{},"number":9,"humanNumber":"9","clue":" Nickname for a seven-time N.B.A. All-Star","direction":"down","length":4,"position":{"x":9,"y":0},"solution":"TMAC"},{"id":"10-down","group":["10-down"],"separatorLocations":{},"number":10,"humanNumber":"10","clue":" Frau's partner","direction":"down","length":4,"position":{"x":10,"y":0},"solution":"HERR"},{"id":"11-down","group":["11-down"],"separatorLocations":{},"number":11,"humanNumber":"11","clue":" Billionaire's home, maybe","direction":"down","length":6,"position":{"x":11,"y":0},"solution":"ESTATE"},{"id":"12-down","group":["12-down"],"separatorLocations":{},"number":12,"humanNumber":"12","clue":" Halfhearted R.S.V.P.'s","direction":"down","length":6,"position":{"x":12,"y":0},"solution":"MAYBES"},{"id":"13-down","group":["13-down"],"separatorLocations":{},"number":13,"humanNumber":"13","clue":" Letter-shaped support","direction":"down","length":5,"position":{"x":14,"y":0},"solution":"IBEAM"},{"id":"14-down","group":["14-down"],"separatorLocations":{},"number":14,"humanNumber":"14","clue":" Bean","direction":"down","length":4,"position":{"x":0,"y":1},"solution":"CONK"},{"id":"15-down","group":["15-down"],"separatorLocations":{},"number":15,"humanNumber":"15","clue":" German finale","direction":"down","length":4,"position":{"x":1,"y":1},"solution":"ENDE"},{"id":"16-down","group":["16-down"],"separatorLocations":{},"number":16,"humanNumber":"16","clue":" \"Brave New World\" drug","direction":"down","length":4,"position":{"x":3,"y":1},"solution":"SOMA"},{"id":"17-down","group":["17-down"],"separatorLocations":{},"number":17,"humanNumber":"17","clue":" ___ eye","direction":"down","length":4,"position":{"x":4,"y":1},"solution":"EVIL"},{"id":"18-down","group":["18-down"],"separatorLocations":{},"number":18,"humanNumber":"18","clue":" Lit part","direction":"down","length":4,"position":{"x":5,"y":1},"solution":"WICK"},{"id":"22-down","group":["22-down"],"separatorLocations":{},"number":22,"humanNumber":"22","clue":" Ashkenazi, for one","direction":"down","length":3,"position":{"x":8,"y":2},"solution":"JEW"},{"id":"24-down","group":["24-down"],"separatorLocations":{},"number":24,"humanNumber":"24","clue":" Take in","direction":"down","length":3,"position":{"x":3,"y":3},"solution":"EAT"},{"id":"28-down","group":["28-down"],"separatorLocations":{},"number":28,"humanNumber":"28","clue":" Polo locale","direction":"down","length":6,"position":{"x":1,"y":5},"solution":"CATHAY"},{"id":"30-down","group":["30-down"],"separatorLocations":{},"number":30,"humanNumber":"30","clue":" New Deal inits.","direction":"down","length":3,"position":{"x":2,"y":6},"solution":"NRA"},{"id":"32-down","group":["32-down"],"separatorLocations":{},"number":32,"humanNumber":"32","clue":" They turn on hinges","direction":"down","length":5,"position":{"x":0,"y":7},"solution":"ULNAE"},{"id":"33-down","group":["33-down"],"separatorLocations":{},"number":33,"humanNumber":"33","clue":" A goner","direction":"down","length":5,"position":{"x":1,"y":7},"solution":"TOAST"},{"id":"34-down","group":["34-down"],"separatorLocations":{},"number":34,"humanNumber":"34","clue":" \"If only!\"","direction":"down","length":5,"position":{"x":2,"y":7},"solution":"IWISH"},{"id":"35-down","group":["35-down"],"separatorLocations":{},"number":35,"humanNumber":"35","clue":" Third-century year","direction":"down","length":3,"position":{"x":3,"y":7},"solution":"CCL"},{"id":"37-down","group":["37-down"],"separatorLocations":{},"number":37,"humanNumber":"37","clue":" \"This ___ outrage!\"","direction":"down","length":4,"position":{"x":9,"y":7},"solution":"ISAN"},{"id":"38-down","group":["38-down"],"separatorLocations":{},"number":38,"humanNumber":"38","clue":" Reciprocal Fibonacci constant","direction":"down","length":3,"position":{"x":10,"y":7},"solution":"PSI"},{"id":"39-down","group":["39-down"],"separatorLocations":{},"number":39,"humanNumber":"39","clue":" Bomb","direction":"down","length":6,"position":{"x":0,"y":8},"solution":"FIASCO"},{"id":"40-down","group":["40-down"],"separatorLocations":{},"number":40,"humanNumber":"40","clue":" Suffix with drunk","direction":"down","length":3,"position":{"x":1,"y":8},"solution":"ARD"},{"id":"41-down","group":["41-down"],"separatorLocations":{},"number":41,"humanNumber":"41","clue":" Desk item","direction":"down","length":7,"position":{"x":2,"y":8},"solution":"STAPLER"},{"id":"42-down","group":["42-down"],"separatorLocations":{},"number":42,"humanNumber":"42","clue":" Kind of wave","direction":"down","length":5,"position":{"x":3,"y":8},"solution":"TIDAL"},{"id":"44-down","group":["44-down"],"separatorLocations":{},"number":44,"humanNumber":"44","clue":" \"___ the season ...\"","direction":"down","length":3,"position":{"x":11,"y":8},"solution":"TIS"},{"id":"45-down","group":["45-down"],"separatorLocations":{},"number":45,"humanNumber":"45","clue":" Black in a cowboy hat","direction":"down","length":5,"position":{"x":12,"y":8},"solution":"CLINT"},{"id":"46-down","group":["46-down"],"separatorLocations":{},"number":46,"humanNumber":"46","clue":" \"Sleigh Ride\" composer Anderson","direction":"down","length":5,"position":{"x":13,"y":8},"solution":"LEROY"},{"id":"48-down","group":["48-down"],"separatorLocations":{},"number":48,"humanNumber":"48","clue":" Enero starts it","direction":"down","length":3,"position":{"x":5,"y":9},"solution":"ANO"},{"id":"49-down","group":["49-down"],"separatorLocations":{},"number":49,"humanNumber":"49","clue":" Times to remember","direction":"down","length":4,"position":{"x":10,"y":9},"solution":"ERAS"},{"id":"50-down","group":["50-down"],"separatorLocations":{},"number":50,"humanNumber":"50","clue":" Med. land","direction":"down","length":3,"position":{"x":11,"y":9},"solution":"SYR"},{"id":"53-down","group":["53-down"],"separatorLocations":{},"number":53,"humanNumber":"53","clue":" Cornelius who wrote \"A Bridge Too Far\"","direction":"down","length":4,"position":{"x":8,"y":10},"solution":"RYAN"},{"id":"54-down","group":["54-down"],"separatorLocations":{},"number":54,"humanNumber":"54","clue":" Creature worshiped by the Incas","direction":"down","length":6,"position":{"x":9,"y":10},"solution":"CONDOR"},{"id":"57-down","group":["57-down"],"separatorLocations":{},"number":57,"humanNumber":"57","clue":" As one","direction":"down","length":6,"position":{"x":11,"y":11},"solution":"ENBLOC"},{"id":"61-down","group":["61-down"],"separatorLocations":{},"number":61,"humanNumber":"61","clue":" Appended","direction":"down","length":7,"position":{"x":12,"y":12},"solution":"ADDEDON"},{"id":"62-down","group":["62-down"],"separatorLocations":{},"number":62,"humanNumber":"62","clue":" Zip","direction":"down","length":3,"position":{"x":13,"y":12},"solution":"NIL"},{"id":"64-down","group":["64-down"],"separatorLocations":{},"number":64,"humanNumber":"64","clue":" 101-Across, e.g.","direction":"down","length":3,"position":{"x":4,"y":13},"solution":"POP"},{"id":"66-down","group":["66-down"],"separatorLocations":{},"number":66,"humanNumber":"66","clue":" Alias initials","direction":"down","length":3,"position":{"x":10,"y":13},"solution":"AKA"},{"id":"68-down","group":["68-down"],"separatorLocations":{},"number":68,"humanNumber":"68","clue":" Bit of homework","direction":"down","length":6,"position":{"x":5,"y":14},"solution":"REPORT"},{"id":"69-down","group":["69-down"],"separatorLocations":{},"number":69,"humanNumber":"69","clue":" Actress ___ Flynn Boyle","direction":"down","length":4,"position":{"x":9,"y":14},"solution":"LARA"},{"id":"70-down","group":["70-down"],"separatorLocations":{},"number":70,"humanNumber":"70","clue":" Rub out","direction":"down","length":5,"position":{"x":13,"y":14},"solution":"ERASE"},{"id":"71-down","group":["71-down"],"separatorLocations":{},"number":71,"humanNumber":"71","clue":" Stimulating","direction":"down","length":5,"position":{"x":14,"y":14},"solution":"JAZZY"},{"id":"72-down","group":["72-down"],"separatorLocations":{},"number":72,"humanNumber":"72","clue":" Gladly","direction":"down","length":4,"position":{"x":7,"y":15},"solution":"LIEF"},{"id":"73-down","group":["73-down"],"separatorLocations":{},"number":73,"humanNumber":"73","clue":" Old cry of dismay","direction":"down","length":5,"position":{"x":8,"y":15},"solution":"ALACK"},{"id":"77-down","group":["77-down"],"separatorLocations":{},"number":77,"humanNumber":"77","clue":" Barks","direction":"down","length":5,"position":{"x":9,"y":16},"solution":"YAWPS"},{"id":"78-down","group":["78-down"],"separatorLocations":{},"number":78,"humanNumber":"78","clue":" Anticipate","direction":"down","length":5,"position":{"x":10,"y":16},"solution":"AWAIT"},{"id":"79-down","group":["79-down"],"separatorLocations":{},"number":79,"humanNumber":"79","clue":" Yucatán youth","direction":"down","length":5,"position":{"x":11,"y":16},"solution":"NENES"},{"id":"80-down","group":["80-down"],"separatorLocations":{},"number":80,"humanNumber":"80","clue":" Howe'er","direction":"down","length":3,"position":{"x":12,"y":16},"solution":"THO"},{"id":"82-down","group":["82-down"],"separatorLocations":{},"number":82,"humanNumber":"82","clue":" \"Treasure Island\" inits.","direction":"down","length":3,"position":{"x":3,"y":17},"solution":"RLS"},{"id":"83-down","group":["83-down"],"separatorLocations":{},"number":83,"humanNumber":"83","clue":" Words before any month's name","direction":"down","length":6,"position":{"x":4,"y":17},"solution":"IDESOF"},{"id":"84-down","group":["84-down"],"separatorLocations":{},"number":84,"humanNumber":"84","clue":" Fortune profilees, for short","direction":"down","length":4,"position":{"x":8,"y":17},"solution":"CEOS"},{"id":"85-down","group":["85-down"],"separatorLocations":{},"number":85,"humanNumber":"85","clue":" \"Uh-huh\"","direction":"down","length":3,"position":{"x":12,"y":17},"solution":"YEP"},{"id":"88-down","group":["88-down"],"separatorLocations":{},"number":88,"humanNumber":"88","clue":" ___ bono (for whose benefit?: Lat.)","direction":"down","length":3,"position":{"x":7,"y":18},"solution":"CUI"},{"id":"89-down","group":["89-down"],"separatorLocations":{},"number":89,"humanNumber":"89","clue":" \"___ Bangs\" (Ricky Martin hit)","direction":"down","length":3,"position":{"x":13,"y":18},"solution":"SHE"},{"id":"91-down","group":["91-down"],"separatorLocations":{},"number":91,"humanNumber":"91","clue":" Check, as text","direction":"down","length":8,"position":{"x":4,"y":19},"solution":"COPYREAD"},{"id":"92-down","group":["92-down"],"separatorLocations":{},"number":92,"humanNumber":"92","clue":" Bklyn. ___","direction":"down","length":3,"position":{"x":5,"y":19},"solution":"HTS"},{"id":"95-down","group":["95-down"],"separatorLocations":{},"number":95,"humanNumber":"95","clue":" Kind of power, in math","direction":"down","length":3,"position":{"x":6,"y":20},"solution":"NTH"},{"id":"98-down","group":["98-down"],"separatorLocations":{},"number":98,"humanNumber":"98","clue":" Outs","direction":"down","length":6,"position":{"x":8,"y":21},"solution":"ALIBIS"},{"id":"99-down","group":["99-down"],"separatorLocations":{},"number":99,"humanNumber":"99","clue":" Speech blocker","direction":"down","length":6,"position":{"x":9,"y":21},"solution":"GAGLAW"},{"id":"101-down","group":["101-down"],"separatorLocations":{},"number":101,"humanNumber":"101","clue":" One going into a drive","direction":"down","length":5,"position":{"x":12,"y":22},"solution":"CDROM"},{"id":"103-down","group":["103-down"],"separatorLocations":{},"number":103,"humanNumber":"103","clue":" Hall's partner","direction":"down","length":5,"position":{"x":4,"y":23},"solution":"OATES"},{"id":"104-down","group":["104-down"],"separatorLocations":{},"number":104,"humanNumber":"104","clue":" Santa ___","direction":"down","length":3,"position":{"x":5,"y":23},"solution":"ANA"},{"id":"105-down","group":["105-down"],"separatorLocations":{},"number":105,"humanNumber":"105","clue":" Bugged","direction":"down","length":5,"position":{"x":6,"y":23},"solution":"GOTTO"},{"id":"106-down","group":["106-down"],"separatorLocations":{},"number":106,"humanNumber":"106","clue":" They take vids","direction":"down","length":4,"position":{"x":12,"y":23},"solution":"CAMS"},{"id":"107-down","group":["107-down"],"separatorLocations":{},"number":107,"humanNumber":"107","clue":" ___ plaisir","direction":"down","length":4,"position":{"x":13,"y":23},"solution":"AVEC"},{"id":"108-down","group":["108-down"],"separatorLocations":{},"number":108,"humanNumber":"108","clue":" \"Oh, pooh!\"","direction":"down","length":4,"position":{"x":14,"y":23},"solution":"TISH"},{"id":"109-down","group":["109-down"],"separatorLocations":{},"number":109,"humanNumber":"109","clue":" Butcher's trimmings","direction":"down","length":3,"position":{"x":0,"y":24},"solution":"FAT"},{"id":"110-down","group":["110-down"],"separatorLocations":{},"number":110,"humanNumber":"110","clue":" Soulful Redding","direction":"down","length":4,"position":{"x":1,"y":24},"solution":"OTIS"},{"id":"111-down","group":["111-down"],"separatorLocations":{},"number":111,"humanNumber":"111","clue":" Slime","direction":"down","length":4,"position":{"x":2,"y":24},"solution":"OOZE"},{"id":"112-down","group":["112-down"],"separatorLocations":{},"number":112,"humanNumber":"112","clue":" Venezuela's Chávez","direction":"down","length":4,"position":{"x":7,"y":24},"solution":"HUGO"},{"id":"113-down","group":["113-down"],"separatorLocations":{},"number":113,"humanNumber":"113","clue":" Colonial land: Abbr.","direction":"down","length":4,"position":{"x":8,"y":24},"solution":"TERR"},{"id":"115-down","group":["115-down"],"separatorLocations":{},"number":115,"humanNumber":"115","clue":" Rose's beau","direction":"down","length":4,"position":{"x":14,"y":24},"solution":"ABIE"},{"id":"116-down","group":["116-down"],"separatorLocations":{},"number":116,"humanNumber":"116","clue":" ___ Bay (Manhattan area)","direction":"down","length":4,"position":{"x":0,"y":25},"solution":"KIPS"},{"id":"117-down","group":["117-down"],"separatorLocations":{},"number":117,"humanNumber":"117","clue":" Sp. titles","direction":"down","length":4,"position":{"x":1,"y":25},"solution":"SRAS"},{"id":"120-down","group":["120-down"],"separatorLocations":{},"number":120,"humanNumber":"120","clue":" But: Lat.","direction":"down","length":3,"position":{"x":0,"y":26},"solution":"SED"},{"id":"121-down","group":["121-down"],"separatorLocations":{},"number":121,"humanNumber":"121","clue":" Some evidence","direction":"down","length":3,"position":{"x":8,"y":26},"solution":"DNA"}],"dimensions":{"cols":21,"rows":21},"crosswordType":"genius"}